{
  "created": 1657765476,
  "d1": "ia601502.us.archive.org",
  "d2": "ia801502.us.archive.org",
  "dir": "/20/items/highcountrynews-2022",
  "files": [
    {
      "name": "__ia_thumb.jpg",
      "source": "original",
      "mtime": "1657339178",
      "size": "18438",
      "md5": "1a08a31ae25b8afe4c28db317ca2d0d2",
      "crc32": "7ff77d94",
      "sha1": "6c303d1684ecb34cba79cc00a170bc55e7c23985",
      "format": "Item Tile",
      "rotation": "0"
    },
    {
      "name": "highcountrynews-2022-07-08T21:58:44.212934-06:00.accessibility.json",
      "source": "original",
      "mtime": "1657339140",
      "size": "44960",
      "md5": "8e9e4814cb99e51ef124ab97fb825430",
      "crc32": "175391c2",
      "sha1": "e07f922b4e7c8683b8eaae3f06f83ea1c26c1514",
      "format": "JSON"
    },
    {
      "name": "highcountrynews-2022-07-08T21:58:44.212934-06:00.hyperlinks.json",
      "source": "original",
      "mtime": "1657339142",
      "size": "30093",
      "md5": "1e99812a4c825b69573f97b84948f545",
      "crc32": "3ab8049f",
      "sha1": "c0c6e22177808e8fd3e02a90d07faf0ce2228521",
      "format": "JSON"
    },
    {
      "name": "highcountrynews-2022-07-08T21:58:44.212934-06:00.jpg",
      "source": "original",
      "mtime": "1657339129",
      "size": "349660",
      "md5": "05c55e4936279acef989a04dfc4f1e74",
      "crc32": "8e19373b",
      "sha1": "904431223f630fbc23802e41637ecaa48ff74898",
      "format": "JPEG",
      "rotation": "0"
    },
    {
      "name": "highcountrynews-2022-07-08T21:58:44.212934-06:00_thumb.jpg",
      "source": "derivative",
      "format": "JPEG Thumb",
      "original": "highcountrynews-2022-07-08T21:58:44.212934-06:00.jpg",
      "mtime": "1657339329",
      "size": "10567",
      "md5": "717232ab903e2dcc09ae5eaee5f7d35a",
      "crc32": "3576a290",
      "sha1": "7fc72fa61ed6b2a580356d8dd6336da5705d2a17"
    },
    {
      "name": "highcountrynews-2022-07-09T09:40:58.616694-06:00.accessibility.json",
      "source": "original",
      "mtime": "1657381262",
      "size": "45079",
      "md5": "0da57205cfad6a71de4ccfda1d5dbfda",
      "crc32": "8324c723",
      "sha1": "f672e8e77c10207763844dad5e2aab7081c1a704",
      "format": "JSON"
    },
    {
      "name": "highcountrynews-2022-07-09T09:40:58.616694-06:00.hyperlinks.json",
      "source": "original",
      "mtime": "1657381264",
      "size": "30067",
      "md5": "749a9abc2ded4111f5c09949d47ab5a3",
      "crc32": "ddcee069",
      "sha1": "f6b1a9da3fe7fe2c2630427265340818f71c1912",
      "format": "JSON"
    },
    {
      "name": "highcountrynews-2022-07-09T09:40:58.616694-06:00.jpg",
      "source": "original",
      "mtime": "1657381260",
      "size": "347109",
      "md5": "8d787b247798d0a73c246e79c4fb0ebe",
      "crc32": "f39f5d1e",
      "sha1": "58c2780770c76a2359cb49c25c06d62a4684c64a",
      "format": "JPEG",
      "rotation": "0"
    },
    {
      "name": "highcountrynews-2022-07-09T09:40:58.616694-06:00_thumb.jpg",
      "source": "derivative",
      "format": "JPEG Thumb",
      "original": "highcountrynews-2022-07-09T09:40:58.616694-06:00.jpg",
      "mtime": "1657381312",
      "size": "10503",
      "md5": "81d3091e69820bdd0f9d6b83ad8efcfc",
      "crc32": "7995392c",
      "sha1": "e9515c0538f6636cebab6487727749194b4b6c23"
    },
    {
      "name": "highcountrynews-2022-07-09T22:04:41.459637-06:00.accessibility.json",
      "source": "original",
      "mtime": "1657425889",
      "size": "45079",
      "md5": "0da57205cfad6a71de4ccfda1d5dbfda",
      "crc32": "8324c723",
      "sha1": "f672e8e77c10207763844dad5e2aab7081c1a704",
      "format": "JSON"
    },
    {
      "name": "highcountrynews-2022-07-09T22:04:41.459637-06:00.hyperlinks.json",
      "source": "original",
      "mtime": "1657425891",
      "size": "30067",
      "md5": "749a9abc2ded4111f5c09949d47ab5a3",
      "crc32": "ddcee069",
      "sha1": "f6b1a9da3fe7fe2c2630427265340818f71c1912",
      "format": "JSON"
    },
    {
      "name": "highcountrynews-2022-07-09T22:04:41.459637-06:00.jpg",
      "source": "original",
      "mtime": "1657425884",
      "size": "347109",
      "md5": "8d787b247798d0a73c246e79c4fb0ebe",
      "crc32": "f39f5d1e",
      "sha1": "58c2780770c76a2359cb49c25c06d62a4684c64a",
      "format": "JPEG",
      "rotation": "0"
    },
    {
      "name": "highcountrynews-2022-07-09T22:04:41.459637-06:00_thumb.jpg",
      "source": "derivative",
      "format": "JPEG Thumb",
      "original": "highcountrynews-2022-07-09T22:04:41.459637-06:00.jpg",
      "mtime": "1657425981",
      "size": "10503",
      "md5": "81d3091e69820bdd0f9d6b83ad8efcfc",
      "crc32": "7995392c",
      "sha1": "e9515c0538f6636cebab6487727749194b4b6c23"
    },
    {
      "name": "highcountrynews-2022-07-10T09:42:00.632290-06:00.accessibility.json",
      "source": "original",
      "mtime": "1657467726",
      "size": "45059",
      "md5": "6c297363441f101a8719fb14c7ece1c1",
      "crc32": "22abffd1",
      "sha1": "ac7e16af4e49f846799b378f51ea88ecb9c837dd",
      "format": "JSON"
    },
    {
      "name": "highcountrynews-2022-07-10T09:42:00.632290-06:00.hyperlinks.json",
      "source": "original",
      "mtime": "1657467729",
      "size": "30040",
      "md5": "f51984a06a524fd9215998f1dacf17c4",
      "crc32": "eaa3ba3c",
      "sha1": "79aa9977f36b3105055e4f82351f63928c3b269d",
      "format": "JSON"
    },
    {
      "name": "highcountrynews-2022-07-10T09:42:00.632290-06:00.jpg",
      "source": "original",
      "mtime": "1657467723",
      "size": "346957",
      "md5": "c50e2ff546e5d24f6ee69a2fc0613605",
      "crc32": "c40de42f",
      "sha1": "02b59b028b81187c8ff9ed51752c6149d5d43868",
      "format": "JPEG",
      "rotation": "0"
    },
    {
      "name": "highcountrynews-2022-07-10T09:42:00.632290-06:00_thumb.jpg",
      "source": "derivative",
      "format": "JPEG Thumb",
      "original": "highcountrynews-2022-07-10T09:42:00.632290-06:00.jpg",
      "mtime": "1657467776",
      "size": "10573",
      "md5": "81573f9854c52007fb7cb8950d2fc186",
      "crc32": "0070c514",
      "sha1": "3eadceef730f04f670af5ee07b928cc07b98b194"
    },
    {
      "name": "highcountrynews-2022-07-10T22:06:10.173425-06:00.accessibility.json",
      "source": "original",
      "mtime": "1657512374",
      "size": "45059",
      "md5": "6c297363441f101a8719fb14c7ece1c1",
      "crc32": "22abffd1",
      "sha1": "ac7e16af4e49f846799b378f51ea88ecb9c837dd",
      "format": "JSON"
    },
    {
      "name": "highcountrynews-2022-07-10T22:06:10.173425-06:00.hyperlinks.json",
      "source": "original",
      "mtime": "1657512375",
      "size": "30040",
      "md5": "f51984a06a524fd9215998f1dacf17c4",
      "crc32": "eaa3ba3c",
      "sha1": "79aa9977f36b3105055e4f82351f63928c3b269d",
      "format": "JSON"
    },
    {
      "name": "highcountrynews-2022-07-10T22:06:10.173425-06:00.jpg",
      "source": "original",
      "mtime": "1657512371",
      "size": "346957",
      "md5": "c50e2ff546e5d24f6ee69a2fc0613605",
      "crc32": "c40de42f",
      "sha1": "02b59b028b81187c8ff9ed51752c6149d5d43868",
      "format": "JPEG",
      "rotation": "0"
    },
    {
      "name": "highcountrynews-2022-07-10T22:06:10.173425-06:00_thumb.jpg",
      "source": "derivative",
      "format": "JPEG Thumb",
      "original": "highcountrynews-2022-07-10T22:06:10.173425-06:00.jpg",
      "mtime": "1657512527",
      "size": "10573",
      "md5": "81573f9854c52007fb7cb8950d2fc186",
      "crc32": "0070c514",
      "sha1": "3eadceef730f04f670af5ee07b928cc07b98b194"
    },
    {
      "name": "highcountrynews-2022-07-11T12:41:54.986858-06:00.accessibility.json",
      "source": "original",
      "mtime": "1657564919",
      "size": "44722",
      "md5": "d38668ee42f0c013b4547f5e39586876",
      "crc32": "f0700e60",
      "sha1": "111af14178f1888bf1a5e28cc8f9a6758836ba5e",
      "format": "JSON"
    },
    {
      "name": "highcountrynews-2022-07-11T12:41:54.986858-06:00.hyperlinks.json",
      "source": "original",
      "mtime": "1657564921",
      "size": "29712",
      "md5": "a33d130e237f60de159d50ac260f43c0",
      "crc32": "c6396969",
      "sha1": "95af5c4332526bc1b2a500bcc8cf098eb956d2fe",
      "format": "JSON"
    },
    {
      "name": "highcountrynews-2022-07-11T12:41:54.986858-06:00.jpg",
      "source": "original",
      "mtime": "1657564916",
      "size": "318981",
      "md5": "babf344e4ed0ffd265cb3ca242ffd14a",
      "crc32": "43f189f8",
      "sha1": "b99f353dc2a03be664696f6b74203ed710ffffe4",
      "format": "JPEG",
      "rotation": "0"
    },
    {
      "name": "highcountrynews-2022-07-11T12:41:54.986858-06:00_thumb.jpg",
      "source": "derivative",
      "format": "JPEG Thumb",
      "original": "highcountrynews-2022-07-11T12:41:54.986858-06:00.jpg",
      "mtime": "1657564972",
      "size": "10380",
      "md5": "2993c6c3bf579d78096ee77932d3de01",
      "crc32": "e31cda7e",
      "sha1": "3bdf3a3bcca63db132e53ca1b94d01f7d8d4e26e"
    },
    {
      "name": "highcountrynews-2022-07-11T22:33:13.078739-06:00.accessibility.json",
      "source": "original",
      "mtime": "1657600396",
      "size": "44717",
      "md5": "495370aa61716beed354d7d387d3cc69",
      "crc32": "590c1407",
      "sha1": "840fa6d2a1928d7ce3085f375476efb05b908597",
      "format": "JSON"
    },
    {
      "name": "highcountrynews-2022-07-11T22:33:13.078739-06:00.hyperlinks.json",
      "source": "original",
      "mtime": "1657600397",
      "size": "29627",
      "md5": "4bcdc92823a9ff1c6330d4c0c3ff8074",
      "crc32": "9f32171e",
      "sha1": "5f5a39ecda0d34c8b19ed5f5fcad0c94c4bd3c59",
      "format": "JSON"
    },
    {
      "name": "highcountrynews-2022-07-11T22:33:13.078739-06:00.jpg",
      "source": "original",
      "mtime": "1657600394",
      "size": "315041",
      "md5": "6d9292c034c5331bb45bb0bd5d20abd7",
      "crc32": "e04a9fa9",
      "sha1": "c4376d70fc9f8bbee5e7a3076ec862b64b267152",
      "format": "JPEG",
      "rotation": "0"
    },
    {
      "name": "highcountrynews-2022-07-11T22:33:13.078739-06:00_thumb.jpg",
      "source": "derivative",
      "format": "JPEG Thumb",
      "original": "highcountrynews-2022-07-11T22:33:13.078739-06:00.jpg",
      "mtime": "1657600521",
      "size": "10367",
      "md5": "0c733e0edbcf3994efe4e0704e922c3e",
      "crc32": "68e6c907",
      "sha1": "148da11b0216c70074f517ed876d7817703a1351"
    },
    {
      "name": "highcountrynews-2022-07-12T11:44:38.105970-06:00.accessibility.json",
      "source": "original",
      "mtime": "1657647881",
      "size": "44607",
      "md5": "1513951c34c0b85605617da721a1edba",
      "crc32": "90991fe3",
      "sha1": "ea61e470a57df91ab81e596b5a749029d8aa7d1e",
      "format": "JSON"
    },
    {
      "name": "highcountrynews-2022-07-12T11:44:38.105970-06:00.hyperlinks.json",
      "source": "original",
      "mtime": "1657647883",
      "size": "29636",
      "md5": "fe8378948e549bc3cd217b0d8fc05415",
      "crc32": "f84c00b6",
      "sha1": "3bc47f11bab7095400e76e8e3d00d5ffab87a6bc",
      "format": "JSON"
    },
    {
      "name": "highcountrynews-2022-07-12T11:44:38.105970-06:00.jpg",
      "source": "original",
      "mtime": "1657647880",
      "size": "353039",
      "md5": "d954cb33e8f4eb8473c2fb9a854ae85e",
      "crc32": "23a9375f",
      "sha1": "096f05bb001e5f05892529cc83c6dd8ca570ee50",
      "format": "JPEG",
      "rotation": "0"
    },
    {
      "name": "highcountrynews-2022-07-12T11:44:38.105970-06:00_thumb.jpg",
      "source": "derivative",
      "format": "JPEG Thumb",
      "original": "highcountrynews-2022-07-12T11:44:38.105970-06:00.jpg",
      "mtime": "1657647932",
      "size": "10454",
      "md5": "b88ccaa5e0f25863c8a45de739a5b29d",
      "crc32": "0a3335cb",
      "sha1": "b08b40a66cd3d768a85fa932a50e97993ed1b8c1"
    },
    {
      "name": "highcountrynews-2022-07-12T20:21:05.081511-06:00.accessibility.json",
      "source": "original",
      "mtime": "1657678868",
      "size": "44607",
      "md5": "1513951c34c0b85605617da721a1edba",
      "crc32": "90991fe3",
      "sha1": "ea61e470a57df91ab81e596b5a749029d8aa7d1e",
      "format": "JSON"
    },
    {
      "name": "highcountrynews-2022-07-12T20:21:05.081511-06:00.hyperlinks.json",
      "source": "original",
      "mtime": "1657678869",
      "size": "29636",
      "md5": "fe8378948e549bc3cd217b0d8fc05415",
      "crc32": "f84c00b6",
      "sha1": "3bc47f11bab7095400e76e8e3d00d5ffab87a6bc",
      "format": "JSON"
    },
    {
      "name": "highcountrynews-2022-07-12T20:21:05.081511-06:00.jpg",
      "source": "original",
      "mtime": "1657678866",
      "size": "353039",
      "md5": "d954cb33e8f4eb8473c2fb9a854ae85e",
      "crc32": "23a9375f",
      "sha1": "096f05bb001e5f05892529cc83c6dd8ca570ee50",
      "format": "JPEG",
      "rotation": "0"
    },
    {
      "name": "highcountrynews-2022-07-12T20:21:05.081511-06:00_thumb.jpg",
      "source": "derivative",
      "format": "JPEG Thumb",
      "original": "highcountrynews-2022-07-12T20:21:05.081511-06:00.jpg",
      "mtime": "1657678929",
      "size": "10454",
      "md5": "b88ccaa5e0f25863c8a45de739a5b29d",
      "crc32": "0a3335cb",
      "sha1": "b08b40a66cd3d768a85fa932a50e97993ed1b8c1"
    },
    {
      "name": "highcountrynews-2022-07-13T20:21:25.476739-06:00.accessibility.json",
      "source": "original",
      "mtime": "1657765290",
      "size": "44814",
      "md5": "251639d4ab778c588d1a2bd4b9036a85",
      "crc32": "0c360ab0",
      "sha1": "cba33770189518f2e1b102d58f85017d3882ec89",
      "format": "JSON"
    },
    {
      "name": "highcountrynews-2022-07-13T20:21:25.476739-06:00.hyperlinks.json",
      "source": "original",
      "mtime": "1657765294",
      "size": "29917",
      "md5": "8d5f2f2dfcbe91f9d3f059fabd5e9a13",
      "crc32": "55ab14b3",
      "sha1": "172b408c306c395e368740b4b6c5be5891a990b2",
      "format": "JSON"
    },
    {
      "name": "highcountrynews-2022-07-13T20:21:25.476739-06:00.jpg",
      "source": "original",
      "mtime": "1657765287",
      "size": "365139",
      "md5": "e7634e719e0481e57dcea7948429a320",
      "crc32": "02b4e629",
      "sha1": "c0703de7a4c07d4749520858ead53547053b2ec9",
      "format": "JPEG",
      "rotation": "0"
    },
    {
      "name": "highcountrynews-2022-07-13T20:21:25.476739-06:00_thumb.jpg",
      "source": "derivative",
      "format": "JPEG Thumb",
      "original": "highcountrynews-2022-07-13T20:21:25.476739-06:00.jpg",
      "mtime": "1657765457",
      "size": "10647",
      "md5": "67919acb45c149acd821921efcb84a8d",
      "crc32": "fa292318",
      "sha1": "00e20e87a14bdb84efaab6b2d88f74ce4dbc48cb"
    },
    {
      "name": "highcountrynews-2022_archive.torrent",
      "source": "metadata",
      "btih": "dfc8afdc7282423899e9fc2af49091e201cb4e17",
      "mtime": "1657765465",
      "size": "10430",
      "md5": "6470bf4e3c37dbdae364124c92747953",
      "crc32": "aef6e004",
      "sha1": "b3a43a4e81c5e14e9be0e18e1b71c612a1df5e56",
      "format": "Archive BitTorrent"
    },
    {
      "name": "highcountrynews-2022_files.xml",
      "source": "original",
      "format": "Metadata",
      "md5": "d0dd03a9fc770dd3988349edf3ebf9c4",
      "summation": "md5"
    },
    {
      "name": "highcountrynews-2022_meta.sqlite",
      "source": "original",
      "mtime": "1657765298",
      "size": "61440",
      "md5": "5f9ea92eb848e840b1826c826f69c97d",
      "crc32": "c0cbe52e",
      "sha1": "0952574819ad0a0c42fd6630497e7beb6be1c874",
      "format": "Metadata"
    },
    {
      "name": "highcountrynews-2022_meta.xml",
      "source": "original",
      "mtime": "1657339139",
      "size": "598",
      "md5": "0bb555e2266fdd36cd3d55d2ea1da6e1",
      "crc32": "3633b5b7",
      "sha1": "0c016dc225743c7ca0663a5d1d8a6c6a9ce11dbf",
      "format": "Metadata"
    }
  ],
  "files_count": 45,
  "item_last_updated": 1657765465,
  "item_size": 4386496,
  "metadata": {
    "identifier": "highcountrynews-2022",
    "collection": [
      "news-homepages",
      "additional_collections"
    ],
    "contributor": "https://homepages.news",
    "date": "2022",
    "mediatype": "image",
    "publisher": "https://www.hcn.org/",
    "scanner": "Internet Archive Python library 3.0.2",
    "title": "High Country News homepages in 2022",
    "uploader": "ben.welsh@gmail.com",
    "publicdate": "2022-07-09 03:58:59",
    "addeddate": "2022-07-09 03:58:59"
  },
  "server": "ia601502.us.archive.org",
  "uniq": 283207920,
  "workable_servers": [
    "ia601502.us.archive.org",
    "ia801502.us.archive.org"
  ]
}