{
  "created": 1659811630,
  "d1": "ia601507.us.archive.org",
  "d2": "ia801507.us.archive.org",
  "dir": "/1/items/newrepublic-2022",
  "files": [
    {
      "name": "__ia_thumb.jpg",
      "source": "original",
      "mtime": "1658374609",
      "size": "16402",
      "md5": "4ece9f41ef6fc39d9121d2b779496846",
      "crc32": "45b1bdea",
      "sha1": "409b24de93cede698fd4f6d9ca69fc2f5a4710db",
      "format": "Item Tile",
      "rotation": "0"
    },
    {
      "name": "newrepublic-2022-07-20T23:35:55.700923-04:00.accessibility.json",
      "source": "original",
      "mtime": "1658374572",
      "size": "29345",
      "md5": "c1b7a647fea5d5a603b75a5f5a90e75d",
      "crc32": "a26a4d5f",
      "sha1": "c2fe711a4f4e5388eb4ace578bcc8f6964b47b40",
      "format": "JSON"
    },
    {
      "name": "newrepublic-2022-07-20T23:35:55.700923-04:00.hyperlinks.json",
      "source": "original",
      "mtime": "1658374574",
      "size": "23246",
      "md5": "180ee81d67e70607cb61b0e4f7cddada",
      "crc32": "bc23ca59",
      "sha1": "e588b2ec158b598c692ea39c865fede9aef358ca",
      "format": "JSON"
    },
    {
      "name": "newrepublic-2022-07-20T23:35:55.700923-04:00.jpg",
      "source": "original",
      "mtime": "1658374560",
      "size": "263179",
      "md5": "6400f609e2bbda78453a30707b272207",
      "crc32": "f7bfe4fd",
      "sha1": "2fc26b7236dc0549b65cd08264911128c8da56ab",
      "format": "JPEG",
      "rotation": "0"
    },
    {
      "name": "newrepublic-2022-07-20T23:35:55.700923-04:00_thumb.jpg",
      "source": "derivative",
      "format": "JPEG Thumb",
      "original": "newrepublic-2022-07-20T23:35:55.700923-04:00.jpg",
      "mtime": "1658376160",
      "size": "9577",
      "md5": "3ffdd4712bf40f567a56ed482bf06b45",
      "crc32": "9196bada",
      "sha1": "c5cf1e82fa6673b9a99d10f8a5afdbbe6848d73f"
    },
    {
      "name": "newrepublic-2022-07-21T11:32:09.788196-04:00.accessibility.json",
      "source": "original",
      "mtime": "1658417534",
      "size": "29332",
      "md5": "13c68fa98b6254a22653f1b002855d25",
      "crc32": "19651246",
      "sha1": "e428c1d47c0a3501901656b34134ad12d7359e98",
      "format": "JSON"
    },
    {
      "name": "newrepublic-2022-07-21T11:32:09.788196-04:00.hyperlinks.json",
      "source": "original",
      "mtime": "1658417536",
      "size": "23004",
      "md5": "60ef50f0da6a35cde0f93137ee91f253",
      "crc32": "6f9ed959",
      "sha1": "09c514e538512e7eb990a274dbba4901650e0053",
      "format": "JSON"
    },
    {
      "name": "newrepublic-2022-07-21T11:32:09.788196-04:00.jpg",
      "source": "original",
      "mtime": "1658417531",
      "size": "297718",
      "md5": "24250c20d9748edf696cc52a497a0b32",
      "crc32": "baf9f352",
      "sha1": "c0019c57c9f66535ab5d1ca1a0edc633dce796c9",
      "format": "JPEG",
      "rotation": "0"
    },
    {
      "name": "newrepublic-2022-07-21T11:32:09.788196-04:00_thumb.jpg",
      "source": "derivative",
      "format": "JPEG Thumb",
      "original": "newrepublic-2022-07-21T11:32:09.788196-04:00.jpg",
      "mtime": "1658422400",
      "size": "9794",
      "md5": "f5f04579235eac0e6a4acb85b8afd962",
      "crc32": "100940bd",
      "sha1": "366819efc43b9fbf969ac97b5db3974710993a76"
    },
    {
      "name": "newrepublic-2022-07-21T12:50:13.190487-04:00.accessibility.json",
      "source": "original",
      "mtime": "1658422216",
      "size": "30232",
      "md5": "7b9fa11e94d256fcabc01385c56effe3",
      "crc32": "da9a650d",
      "sha1": "232adea08ed97ae10969956829412cb625410931",
      "format": "JSON"
    },
    {
      "name": "newrepublic-2022-07-21T12:50:13.190487-04:00.hyperlinks.json",
      "source": "original",
      "mtime": "1658422217",
      "size": "24220",
      "md5": "fd03722b68e74cb4952d2ed56ff08a10",
      "crc32": "74136389",
      "sha1": "d7e073cee5f5ca37328adbfdf003fec49a633616",
      "format": "JSON"
    },
    {
      "name": "newrepublic-2022-07-21T12:50:13.190487-04:00.jpg",
      "source": "original",
      "mtime": "1658422214",
      "size": "297619",
      "md5": "559dc1dffe7b6248be2a3512e09ed4d5",
      "crc32": "6e863a5f",
      "sha1": "0b1157be483ba922beedfa99182141a1525c1d04",
      "format": "JPEG",
      "rotation": "0"
    },
    {
      "name": "newrepublic-2022-07-21T12:50:13.190487-04:00_thumb.jpg",
      "source": "derivative",
      "format": "JPEG Thumb",
      "original": "newrepublic-2022-07-21T12:50:13.190487-04:00.jpg",
      "mtime": "1658431951",
      "size": "9807",
      "md5": "200f02e3fa2380d7cf4eba5b4af15af6",
      "crc32": "8aa659fa",
      "sha1": "42ae250c7dbb1742d48f8b21500414b2341b262d"
    },
    {
      "name": "newrepublic-2022-07-21T23:37:32.995851-04:00.accessibility.json",
      "source": "original",
      "mtime": "1658461055",
      "size": "29478",
      "md5": "5be70d4dc8ba924a25c007575daef0dd",
      "crc32": "f9b98fd4",
      "sha1": "d42e1009e6e142aac382986471ced5a7169e8142",
      "format": "JSON"
    },
    {
      "name": "newrepublic-2022-07-21T23:37:32.995851-04:00.hyperlinks.json",
      "source": "original",
      "mtime": "1658461057",
      "size": "24813",
      "md5": "c70fa08531f8d2a8124e3855464b9bb6",
      "crc32": "f9e9c515",
      "sha1": "d232fef8dad88f05bcbebd99974e5c9530dbf1b0",
      "format": "JSON"
    },
    {
      "name": "newrepublic-2022-07-21T23:37:32.995851-04:00.jpg",
      "source": "original",
      "mtime": "1658461054",
      "size": "282714",
      "md5": "feb849d32b011949d12617eb4802be9a",
      "crc32": "19fdd71f",
      "sha1": "ad96a57348b2734bd0076f5823c5c5e86c715029",
      "format": "JPEG",
      "rotation": "0"
    },
    {
      "name": "newrepublic-2022-07-21T23:37:32.995851-04:00_thumb.jpg",
      "source": "derivative",
      "format": "JPEG Thumb",
      "original": "newrepublic-2022-07-21T23:37:32.995851-04:00.jpg",
      "mtime": "1658470632",
      "size": "9882",
      "md5": "afcb9e05e2ac23eb3ca705e506c9bfff",
      "crc32": "278c0608",
      "sha1": "80ff69d387fa5fd148b15de0e15a75dc986f2ef3"
    },
    {
      "name": "newrepublic-2022-07-22T10:58:47.323617-04:00.accessibility.json",
      "source": "original",
      "mtime": "1658501929",
      "size": "29751",
      "md5": "8434e738865090d2f861a5971d0c51e2",
      "crc32": "217b8e59",
      "sha1": "bf128583944ff04e96536330a007bd39d5b3e2b2",
      "format": "JSON"
    },
    {
      "name": "newrepublic-2022-07-22T10:58:47.323617-04:00.hyperlinks.json",
      "source": "original",
      "mtime": "1658501931",
      "size": "22963",
      "md5": "2eb444500500b266649dbf17825276aa",
      "crc32": "eda2504b",
      "sha1": "5470ab992b698f9d09dad1afce71c487663b001d",
      "format": "JSON"
    },
    {
      "name": "newrepublic-2022-07-22T10:58:47.323617-04:00.jpg",
      "source": "original",
      "mtime": "1658501928",
      "size": "300197",
      "md5": "d4e83f5064feb0c380eb0a62bc504ac6",
      "crc32": "084d98b4",
      "sha1": "0e83608172da4f45c8f4a455024bda1d174bac66",
      "format": "JPEG",
      "rotation": "0"
    },
    {
      "name": "newrepublic-2022-07-22T10:58:47.323617-04:00_thumb.jpg",
      "source": "derivative",
      "format": "JPEG Thumb",
      "original": "newrepublic-2022-07-22T10:58:47.323617-04:00.jpg",
      "mtime": "1658506357",
      "size": "10107",
      "md5": "323a5ea18c13d54bcd5a262b95d81cb0",
      "crc32": "784c1f91",
      "sha1": "1aa678a790d056655eb7eda83b27eeed6c0e26cf"
    },
    {
      "name": "newrepublic-2022-07-22T12:12:04.484435-04:00.accessibility.json",
      "source": "original",
      "mtime": "1658506329",
      "size": "28731",
      "md5": "4605ac6bdc024dad54a7e24622e99336",
      "crc32": "a327dfa5",
      "sha1": "8ed7b5ad07a0780377e502be85ce5a10290b6853",
      "format": "JSON"
    },
    {
      "name": "newrepublic-2022-07-22T12:12:04.484435-04:00.hyperlinks.json",
      "source": "original",
      "mtime": "1658506330",
      "size": "22963",
      "md5": "2eb444500500b266649dbf17825276aa",
      "crc32": "eda2504b",
      "sha1": "5470ab992b698f9d09dad1afce71c487663b001d",
      "format": "JSON"
    },
    {
      "name": "newrepublic-2022-07-22T12:12:04.484435-04:00.jpg",
      "source": "original",
      "mtime": "1658506326",
      "size": "304759",
      "md5": "aaa63b3eabf0495436dad0ad976dc762",
      "crc32": "396b8275",
      "sha1": "5382f84983d2c8f566532d4642ad895f5050c65a",
      "format": "JPEG",
      "rotation": "0"
    },
    {
      "name": "newrepublic-2022-07-22T12:12:04.484435-04:00_thumb.jpg",
      "source": "derivative",
      "format": "JPEG Thumb",
      "original": "newrepublic-2022-07-22T12:12:04.484435-04:00.jpg",
      "mtime": "1658524519",
      "size": "10158",
      "md5": "8213faeb03fc99731072f77192f475d9",
      "crc32": "6c920483",
      "sha1": "76dc731e6334ae9c7e472a334532b05c7f5be98e"
    },
    {
      "name": "newrepublic-2022-07-22T23:33:10.518952-04:00.accessibility.json",
      "source": "original",
      "mtime": "1658547194",
      "size": "29779",
      "md5": "d5b3227628a2cf75409862cd7e0491af",
      "crc32": "56fea16f",
      "sha1": "e0fc0bc7b761425e8c73c96013f76ca4b671e380",
      "format": "JSON"
    },
    {
      "name": "newrepublic-2022-07-22T23:33:10.518952-04:00.hyperlinks.json",
      "source": "original",
      "mtime": "1658547195",
      "size": "23261",
      "md5": "0c0855831fc0f511010ace2a21b1a441",
      "crc32": "588487f4",
      "sha1": "9f5e11402d5c0dfd691079e6ce0a21490483c10e",
      "format": "JSON"
    },
    {
      "name": "newrepublic-2022-07-22T23:33:10.518952-04:00.jpg",
      "source": "original",
      "mtime": "1658547192",
      "size": "290702",
      "md5": "7b2a3d87149b37d9da347664b4366255",
      "crc32": "cb87f2f6",
      "sha1": "a9ea166942be5184ef1fcbacc05d4e5e6cbd1ba0",
      "format": "JPEG",
      "rotation": "0"
    },
    {
      "name": "newrepublic-2022-07-22T23:33:10.518952-04:00_thumb.jpg",
      "source": "derivative",
      "format": "JPEG Thumb",
      "original": "newrepublic-2022-07-22T23:33:10.518952-04:00.jpg",
      "mtime": "1658551343",
      "size": "9779",
      "md5": "e7c2748e85a2c528bac623d6d14d6064",
      "crc32": "83cdf679",
      "sha1": "3d186019a729e3a44c9b108f5d081378025fcba0"
    },
    {
      "name": "newrepublic-2022-07-23T11:02:42.368282-04:00.accessibility.json",
      "source": "original",
      "mtime": "1658588565",
      "size": "28717",
      "md5": "cad0db20aa7cb229b6f259b7ec5b8eb6",
      "crc32": "219ce0ec",
      "sha1": "6725a753d9b09b4f5e981bdf2198d5f14ab77fe3",
      "format": "JSON"
    },
    {
      "name": "newrepublic-2022-07-23T11:02:42.368282-04:00.hyperlinks.json",
      "source": "original",
      "mtime": "1658588567",
      "size": "23227",
      "md5": "eff1707a30d49db016f65d303f938440",
      "crc32": "91bdd905",
      "sha1": "c7bfc0eda1fbb06890b6056387067a4034da1c65",
      "format": "JSON"
    },
    {
      "name": "newrepublic-2022-07-23T11:02:42.368282-04:00.jpg",
      "source": "original",
      "mtime": "1658588564",
      "size": "306564",
      "md5": "b2dd354d815d22f5df2dfa7dd0ce230e",
      "crc32": "b5d54eab",
      "sha1": "cb5c41dded2772ef9d11ccd00d95a5d40140af77",
      "format": "JPEG",
      "rotation": "0"
    },
    {
      "name": "newrepublic-2022-07-23T11:02:42.368282-04:00_thumb.jpg",
      "source": "derivative",
      "format": "JPEG Thumb",
      "original": "newrepublic-2022-07-23T11:02:42.368282-04:00.jpg",
      "mtime": "1658588713",
      "size": "9999",
      "md5": "2873aa0cc9f86759a5cd39584ccb3d18",
      "crc32": "d4d96d60",
      "sha1": "a6473e5acbd0e0c825d90e25ca612c622caaa293"
    },
    {
      "name": "newrepublic-2022-07-23T14:13:28.351550-04:00.accessibility.json",
      "source": "original",
      "mtime": "1658600011",
      "size": "28615",
      "md5": "1b9f2dc07b758e42a8792750bd2f37f7",
      "crc32": "f68d0f42",
      "sha1": "c162f3f0c1c76b73574897b6c95fac437de5b229",
      "format": "JSON"
    },
    {
      "name": "newrepublic-2022-07-23T14:13:28.351550-04:00.hyperlinks.json",
      "source": "original",
      "mtime": "1658600013",
      "size": "22842",
      "md5": "13694895d2fa9907e59005e36badce65",
      "crc32": "37c98656",
      "sha1": "2b891b006f781f4be02cbd8958a8c958995f582e",
      "format": "JSON"
    },
    {
      "name": "newrepublic-2022-07-23T14:13:28.351550-04:00.jpg",
      "source": "original",
      "mtime": "1658600010",
      "size": "343080",
      "md5": "de513d9f944b7f5c68c827ce6bca3041",
      "crc32": "b5b177c0",
      "sha1": "fbe05dda6c870b4df92f43edc38688c21730751a",
      "format": "JPEG",
      "rotation": "0"
    },
    {
      "name": "newrepublic-2022-07-23T14:13:28.351550-04:00.lighthouse.json",
      "source": "original",
      "mtime": "1658600015",
      "size": "1467",
      "md5": "d7e1fcb324cf5b7e8a16fcb0ae2aed18",
      "crc32": "ed0edf3d",
      "sha1": "4b977182c7338e973eb5cdd1555b8be5190d8897",
      "format": "JSON"
    },
    {
      "name": "newrepublic-2022-07-23T14:13:28.351550-04:00_thumb.jpg",
      "source": "derivative",
      "format": "JPEG Thumb",
      "original": "newrepublic-2022-07-23T14:13:28.351550-04:00.jpg",
      "mtime": "1658600195",
      "size": "10268",
      "md5": "46d27eb78a4bf18ce3c8aec54456da04",
      "crc32": "5c18e738",
      "sha1": "6922dc42ea6789cf55c0cf7e471264c321cfcf5f"
    },
    {
      "name": "newrepublic-2022-07-24T00:20:05.179476-04:00.accessibility.json",
      "source": "original",
      "mtime": "1658636408",
      "size": "29577",
      "md5": "40a91c2844a94623b13b9ed197c8c629",
      "crc32": "0a33abbf",
      "sha1": "de85b7a97f71d8f456e60eff28493f816d25c2f7",
      "format": "JSON"
    },
    {
      "name": "newrepublic-2022-07-24T00:20:05.179476-04:00.hyperlinks.json",
      "source": "original",
      "mtime": "1658636409",
      "size": "22842",
      "md5": "13694895d2fa9907e59005e36badce65",
      "crc32": "37c98656",
      "sha1": "2b891b006f781f4be02cbd8958a8c958995f582e",
      "format": "JSON"
    },
    {
      "name": "newrepublic-2022-07-24T00:20:05.179476-04:00.jpg",
      "source": "original",
      "mtime": "1658636406",
      "size": "343080",
      "md5": "de513d9f944b7f5c68c827ce6bca3041",
      "crc32": "b5b177c0",
      "sha1": "fbe05dda6c870b4df92f43edc38688c21730751a",
      "format": "JPEG",
      "rotation": "0"
    },
    {
      "name": "newrepublic-2022-07-24T00:20:05.179476-04:00.lighthouse.json",
      "source": "original",
      "mtime": "1658636411",
      "size": "1468",
      "md5": "e6d742844c3a73668e0bd1516353ce91",
      "crc32": "dfb95995",
      "sha1": "50020740ad72475c7214fbaf83fe1d3eddce925c",
      "format": "JSON"
    },
    {
      "name": "newrepublic-2022-07-24T00:20:05.179476-04:00_thumb.jpg",
      "source": "derivative",
      "format": "JPEG Thumb",
      "original": "newrepublic-2022-07-24T00:20:05.179476-04:00.jpg",
      "mtime": "1658636690",
      "size": "10268",
      "md5": "46d27eb78a4bf18ce3c8aec54456da04",
      "crc32": "5c18e738",
      "sha1": "6922dc42ea6789cf55c0cf7e471264c321cfcf5f"
    },
    {
      "name": "newrepublic-2022-07-24T09:05:04.208060-04:00.accessibility.json",
      "source": "original",
      "mtime": "1658667907",
      "size": "28622",
      "md5": "7f2a643ff7e9d021b1c318cef76709d0",
      "crc32": "a40379a0",
      "sha1": "c39e8ea568b5e98c21aba95b11e7c0bf50311cea",
      "format": "JSON"
    },
    {
      "name": "newrepublic-2022-07-24T09:05:04.208060-04:00.hyperlinks.json",
      "source": "original",
      "mtime": "1658667909",
      "size": "22842",
      "md5": "13694895d2fa9907e59005e36badce65",
      "crc32": "37c98656",
      "sha1": "2b891b006f781f4be02cbd8958a8c958995f582e",
      "format": "JSON"
    },
    {
      "name": "newrepublic-2022-07-24T09:05:04.208060-04:00.jpg",
      "source": "original",
      "mtime": "1658667906",
      "size": "343080",
      "md5": "de513d9f944b7f5c68c827ce6bca3041",
      "crc32": "b5b177c0",
      "sha1": "fbe05dda6c870b4df92f43edc38688c21730751a",
      "format": "JPEG",
      "rotation": "0"
    },
    {
      "name": "newrepublic-2022-07-24T09:05:04.208060-04:00.lighthouse.json",
      "source": "original",
      "mtime": "1658667911",
      "size": "1468",
      "md5": "8373cbb70297cf488ca373b0f2d5918e",
      "crc32": "17fa7d85",
      "sha1": "3659657b39a44305e91946c0eafa508b5c100791",
      "format": "JSON"
    },
    {
      "name": "newrepublic-2022-07-24T09:05:04.208060-04:00_thumb.jpg",
      "source": "derivative",
      "format": "JPEG Thumb",
      "original": "newrepublic-2022-07-24T09:05:04.208060-04:00.jpg",
      "mtime": "1658667968",
      "size": "10268",
      "md5": "46d27eb78a4bf18ce3c8aec54456da04",
      "crc32": "5c18e738",
      "sha1": "6922dc42ea6789cf55c0cf7e471264c321cfcf5f"
    },
    {
      "name": "newrepublic-2022-07-24T11:42:49.437434-04:00.accessibility.json",
      "source": "original",
      "mtime": "1658677372",
      "size": "29577",
      "md5": "40a91c2844a94623b13b9ed197c8c629",
      "crc32": "0a33abbf",
      "sha1": "de85b7a97f71d8f456e60eff28493f816d25c2f7",
      "format": "JSON"
    },
    {
      "name": "newrepublic-2022-07-24T11:42:49.437434-04:00.hyperlinks.json",
      "source": "original",
      "mtime": "1658677374",
      "size": "22842",
      "md5": "13694895d2fa9907e59005e36badce65",
      "crc32": "37c98656",
      "sha1": "2b891b006f781f4be02cbd8958a8c958995f582e",
      "format": "JSON"
    },
    {
      "name": "newrepublic-2022-07-24T11:42:49.437434-04:00.jpg",
      "source": "original",
      "mtime": "1658677371",
      "size": "343080",
      "md5": "de513d9f944b7f5c68c827ce6bca3041",
      "crc32": "b5b177c0",
      "sha1": "fbe05dda6c870b4df92f43edc38688c21730751a",
      "format": "JPEG",
      "rotation": "0"
    },
    {
      "name": "newrepublic-2022-07-24T11:42:49.437434-04:00.lighthouse.json",
      "source": "original",
      "mtime": "1658677375",
      "size": "1467",
      "md5": "c68cc7b2212ca9d332d6732fd3100748",
      "crc32": "952e9d92",
      "sha1": "b963079ab8c1f5ae165e450da719a4bf2cbed8b7",
      "format": "JSON"
    },
    {
      "name": "newrepublic-2022-07-24T11:42:49.437434-04:00_thumb.jpg",
      "source": "derivative",
      "format": "JPEG Thumb",
      "original": "newrepublic-2022-07-24T11:42:49.437434-04:00.jpg",
      "mtime": "1658677492",
      "size": "10268",
      "md5": "46d27eb78a4bf18ce3c8aec54456da04",
      "crc32": "5c18e738",
      "sha1": "6922dc42ea6789cf55c0cf7e471264c321cfcf5f"
    },
    {
      "name": "newrepublic-2022-07-24T23:35:37.023623-04:00.accessibility.json",
      "source": "original",
      "mtime": "1658720139",
      "size": "29584",
      "md5": "4877d9fa69b302b977e06c98568ab801",
      "crc32": "e01363d2",
      "sha1": "7bc9bb3dfd998ec274e72deb1efeaaa62f92ee0d",
      "format": "JSON"
    },
    {
      "name": "newrepublic-2022-07-24T23:35:37.023623-04:00.hyperlinks.json",
      "source": "original",
      "mtime": "1658720140",
      "size": "22786",
      "md5": "a7446df426507e600ddab577f7ba1a7a",
      "crc32": "dc9201d0",
      "sha1": "c41f1931d7a0c363992e127fea62c989a1ee0cb5",
      "format": "JSON"
    },
    {
      "name": "newrepublic-2022-07-24T23:35:37.023623-04:00.jpg",
      "source": "original",
      "mtime": "1658720137",
      "size": "343080",
      "md5": "de513d9f944b7f5c68c827ce6bca3041",
      "crc32": "b5b177c0",
      "sha1": "fbe05dda6c870b4df92f43edc38688c21730751a",
      "format": "JPEG",
      "rotation": "0"
    },
    {
      "name": "newrepublic-2022-07-24T23:35:37.023623-04:00.lighthouse.json",
      "source": "original",
      "mtime": "1658720141",
      "size": "1468",
      "md5": "7cb51064712b9e6a2e62c3a588336b60",
      "crc32": "3a02dddd",
      "sha1": "d1f9ae771a75491864f6a80d08db5d587e82876c",
      "format": "JSON"
    },
    {
      "name": "newrepublic-2022-07-24T23:35:37.023623-04:00_thumb.jpg",
      "source": "derivative",
      "format": "JPEG Thumb",
      "original": "newrepublic-2022-07-24T23:35:37.023623-04:00.jpg",
      "mtime": "1658720205",
      "size": "10268",
      "md5": "46d27eb78a4bf18ce3c8aec54456da04",
      "crc32": "5c18e738",
      "sha1": "6922dc42ea6789cf55c0cf7e471264c321cfcf5f"
    },
    {
      "name": "newrepublic-2022-07-25T09:16:31.270508-04:00.accessibility.json",
      "source": "original",
      "mtime": "1658754993",
      "size": "28077",
      "md5": "ca15d61aa967a650ec3d2045c6c7dcc8",
      "crc32": "05702d80",
      "sha1": "98fb1c74f7b70f94e412879da656cb97b289ddd7",
      "format": "JSON"
    },
    {
      "name": "newrepublic-2022-07-25T09:16:31.270508-04:00.hyperlinks.json",
      "source": "original",
      "mtime": "1658754995",
      "size": "22842",
      "md5": "13694895d2fa9907e59005e36badce65",
      "crc32": "37c98656",
      "sha1": "2b891b006f781f4be02cbd8958a8c958995f582e",
      "format": "JSON"
    },
    {
      "name": "newrepublic-2022-07-25T09:16:31.270508-04:00.jpg",
      "source": "original",
      "mtime": "1658754992",
      "size": "343080",
      "md5": "de513d9f944b7f5c68c827ce6bca3041",
      "crc32": "b5b177c0",
      "sha1": "fbe05dda6c870b4df92f43edc38688c21730751a",
      "format": "JPEG",
      "rotation": "0"
    },
    {
      "name": "newrepublic-2022-07-25T09:16:31.270508-04:00.lighthouse.json",
      "source": "original",
      "mtime": "1658754996",
      "size": "1466",
      "md5": "67e1fcb9be074e10c6eba1dc459d90f0",
      "crc32": "57f0668e",
      "sha1": "233de6e6a704a4b3ec13db71461d19094a875548",
      "format": "JSON"
    },
    {
      "name": "newrepublic-2022-07-25T09:16:31.270508-04:00_thumb.jpg",
      "source": "derivative",
      "format": "JPEG Thumb",
      "original": "newrepublic-2022-07-25T09:16:31.270508-04:00.jpg",
      "mtime": "1658762711",
      "size": "10268",
      "md5": "46d27eb78a4bf18ce3c8aec54456da04",
      "crc32": "5c18e738",
      "sha1": "6922dc42ea6789cf55c0cf7e471264c321cfcf5f"
    },
    {
      "name": "newrepublic-2022-07-25T12:37:21.171122-04:00.accessibility.json",
      "source": "original",
      "mtime": "1658767045",
      "size": "29132",
      "md5": "a6033978909bb5c30c23cf2a0cc2b223",
      "crc32": "b0772a34",
      "sha1": "1d69faec01ecf1b4fa50641acdc49211c5392bf9",
      "format": "JSON"
    },
    {
      "name": "newrepublic-2022-07-25T12:37:21.171122-04:00.hyperlinks.json",
      "source": "original",
      "mtime": "1658767046",
      "size": "23633",
      "md5": "6373707751e56875c5e682f20bbc5a1c",
      "crc32": "74758895",
      "sha1": "c29b8267a6a26f158c8a88fbb82aabf52921e24e",
      "format": "JSON"
    },
    {
      "name": "newrepublic-2022-07-25T12:37:21.171122-04:00.jpg",
      "source": "original",
      "mtime": "1658767043",
      "size": "312064",
      "md5": "24ce471a05ba84a13a2ee39d347de2fd",
      "crc32": "24a0854f",
      "sha1": "9143d3f9657718105b2217e872450cf5e376d686",
      "format": "JPEG",
      "rotation": "0"
    },
    {
      "name": "newrepublic-2022-07-25T12:37:21.171122-04:00.lighthouse.json",
      "source": "original",
      "mtime": "1658767048",
      "size": "1468",
      "md5": "dbc25f3dc8c3c62fa656d35fbcf1e00e",
      "crc32": "76f25485",
      "sha1": "58888d01d43dd5049c9bb7e3f271fe61a4ad82a2",
      "format": "JSON"
    },
    {
      "name": "newrepublic-2022-07-25T12:37:21.171122-04:00_thumb.jpg",
      "source": "derivative",
      "format": "JPEG Thumb",
      "original": "newrepublic-2022-07-25T12:37:21.171122-04:00.jpg",
      "mtime": "1658773055",
      "size": "10233",
      "md5": "c75d8aec7dc688b52f03a633f48e4b49",
      "crc32": "4f3f591a",
      "sha1": "1362fd3e8d6e32835a70132e7e52bef3eb1d84f0"
    },
    {
      "name": "newrepublic-2022-07-25T14:40:43.515872-04:00.accessibility.json",
      "source": "original",
      "mtime": "1658774446",
      "size": "29130",
      "md5": "8a2a89a7cf8553c3e1285ae941aecc21",
      "crc32": "567a95bc",
      "sha1": "003fc76da92241d40edb217082df4ea6e25fc3ef",
      "format": "JSON"
    },
    {
      "name": "newrepublic-2022-07-25T14:40:43.515872-04:00.hyperlinks.json",
      "source": "original",
      "mtime": "1658774448",
      "size": "23145",
      "md5": "17b844d2b114e2c75d23535c5d9f88d9",
      "crc32": "d884c57b",
      "sha1": "747bf0d83b11810196d9820a1e0865d58771949d",
      "format": "JSON"
    },
    {
      "name": "newrepublic-2022-07-25T14:40:43.515872-04:00.jpg",
      "source": "original",
      "mtime": "1658774445",
      "size": "351229",
      "md5": "71a83b16857e2a437bfe5f5fca935b81",
      "crc32": "adf3f411",
      "sha1": "11102ffb095d294734bc858d3e1240f6bcedec81",
      "format": "JPEG",
      "rotation": "0"
    },
    {
      "name": "newrepublic-2022-07-25T14:40:43.515872-04:00.lighthouse.json",
      "source": "original",
      "mtime": "1658774449",
      "size": "1467",
      "md5": "4ee572f572c8e2c6d8d4f8a65701f739",
      "crc32": "399fe205",
      "sha1": "490f593cab9c3a4352264d150d144c200b26dd76",
      "format": "JSON"
    },
    {
      "name": "newrepublic-2022-07-25T14:40:43.515872-04:00_thumb.jpg",
      "source": "derivative",
      "format": "JPEG Thumb",
      "original": "newrepublic-2022-07-25T14:40:43.515872-04:00.jpg",
      "mtime": "1658778886",
      "size": "10630",
      "md5": "3a7251e90a3502d3b05b2997b4955bb7",
      "crc32": "86e0d396",
      "sha1": "4ea9bc1edbba6a4ebaa946df5b14c7b40bdb9b78"
    },
    {
      "name": "newrepublic-2022-07-25T22:48:53.877940-04:00.accessibility.json",
      "source": "original",
      "mtime": "1658803737",
      "size": "29130",
      "md5": "8a2a89a7cf8553c3e1285ae941aecc21",
      "crc32": "567a95bc",
      "sha1": "003fc76da92241d40edb217082df4ea6e25fc3ef",
      "format": "JSON"
    },
    {
      "name": "newrepublic-2022-07-25T22:48:53.877940-04:00.hyperlinks.json",
      "source": "original",
      "mtime": "1658803739",
      "size": "23201",
      "md5": "a20d3fe79025c25ba4feffcaf0b62abf",
      "crc32": "9d3de3cf",
      "sha1": "8217e24789b6bdc0f1f68412f5fe35ee9c1c267b",
      "format": "JSON"
    },
    {
      "name": "newrepublic-2022-07-25T22:48:53.877940-04:00.jpg",
      "source": "original",
      "mtime": "1658803735",
      "size": "351229",
      "md5": "71a83b16857e2a437bfe5f5fca935b81",
      "crc32": "adf3f411",
      "sha1": "11102ffb095d294734bc858d3e1240f6bcedec81",
      "format": "JPEG",
      "rotation": "0"
    },
    {
      "name": "newrepublic-2022-07-25T22:48:53.877940-04:00.lighthouse.json",
      "source": "original",
      "mtime": "1658803740",
      "size": "1468",
      "md5": "8c9bc935ec96e33c160460878ccf5adc",
      "crc32": "03ead94a",
      "sha1": "b1cbcd5221844c7085ccd7aea4ebc8e355dc31df",
      "format": "JSON"
    },
    {
      "name": "newrepublic-2022-07-25T22:48:53.877940-04:00_thumb.jpg",
      "source": "derivative",
      "format": "JPEG Thumb",
      "original": "newrepublic-2022-07-25T22:48:53.877940-04:00.jpg",
      "mtime": "1658805043",
      "size": "10630",
      "md5": "3a7251e90a3502d3b05b2997b4955bb7",
      "crc32": "86e0d396",
      "sha1": "4ea9bc1edbba6a4ebaa946df5b14c7b40bdb9b78"
    },
    {
      "name": "newrepublic-2022-07-26T10:41:47.145974-04:00.accessibility.json",
      "source": "original",
      "mtime": "1658846510",
      "size": "29402",
      "md5": "a521db7c9e6155f04c07e12ca96d5545",
      "crc32": "bb814196",
      "sha1": "0d5edb9ad27f9e3464147cefb7bc4387c691f90c",
      "format": "JSON"
    },
    {
      "name": "newrepublic-2022-07-26T10:41:47.145974-04:00.hyperlinks.json",
      "source": "original",
      "mtime": "1658846512",
      "size": "23042",
      "md5": "81bda535314df204fcb1a167110273be",
      "crc32": "aac1ceee",
      "sha1": "e83727cc36256cc8efe5a072cefc5b910719e9b1",
      "format": "JSON"
    },
    {
      "name": "newrepublic-2022-07-26T10:41:47.145974-04:00.jpg",
      "source": "original",
      "mtime": "1658846508",
      "size": "327185",
      "md5": "33df46a9397d3ccf856a0062c7ab4267",
      "crc32": "854fcf84",
      "sha1": "de405e819d467f5e6bf6fc124a67ba8a4d3f0bc5",
      "format": "JPEG",
      "rotation": "0"
    },
    {
      "name": "newrepublic-2022-07-26T10:41:47.145974-04:00.lighthouse.json",
      "source": "original",
      "mtime": "1658846513",
      "size": "1468",
      "md5": "62f4d32ed523ae4f3060ffc10c165010",
      "crc32": "85218315",
      "sha1": "af09f229499ae054a4b3c0595e732cd96e28327e",
      "format": "JSON"
    },
    {
      "name": "newrepublic-2022-07-26T10:41:47.145974-04:00_thumb.jpg",
      "source": "derivative",
      "format": "JPEG Thumb",
      "original": "newrepublic-2022-07-26T10:41:47.145974-04:00.jpg",
      "mtime": "1658857018",
      "size": "10284",
      "md5": "eca66c88be8200b14fe60fb5a81f9521",
      "crc32": "b75759bb",
      "sha1": "18733c14e1e0dfd0d59ef43daba4ed1d92545417"
    },
    {
      "name": "newrepublic-2022-07-26T14:37:10.495665-04:00.accessibility.json",
      "source": "original",
      "mtime": "1658860633",
      "size": "29478",
      "md5": "c86e2438467632904de8ef031ed65193",
      "crc32": "aa39b18d",
      "sha1": "64c3422ee1a7473fcfc9e6dd10e67126e8eb9103",
      "format": "JSON"
    },
    {
      "name": "newrepublic-2022-07-26T14:37:10.495665-04:00.hyperlinks.json",
      "source": "original",
      "mtime": "1658860634",
      "size": "23313",
      "md5": "dcffaa58461939fe9e71149b90057b9a",
      "crc32": "57a6f988",
      "sha1": "ff0967dfdcf23f6721d38a1cb4d93f2e73b5a824",
      "format": "JSON"
    },
    {
      "name": "newrepublic-2022-07-26T14:37:10.495665-04:00.jpg",
      "source": "original",
      "mtime": "1658860631",
      "size": "276216",
      "md5": "387585dada023ef80504c9434eb5b5c0",
      "crc32": "38191907",
      "sha1": "5798adc58a6282f88f00d09e0d4c0447b969a3e0",
      "format": "JPEG",
      "rotation": "0"
    },
    {
      "name": "newrepublic-2022-07-26T14:37:10.495665-04:00.lighthouse.json",
      "source": "original",
      "mtime": "1658860636",
      "size": "1467",
      "md5": "3666e56b09263c7397bcc4d38a4c54be",
      "crc32": "5e8fa46f",
      "sha1": "00d2ac7280ef1db3e8ccce4f5a4c6325b2f0ae17",
      "format": "JSON"
    },
    {
      "name": "newrepublic-2022-07-26T14:37:10.495665-04:00_thumb.jpg",
      "source": "derivative",
      "format": "JPEG Thumb",
      "original": "newrepublic-2022-07-26T14:37:10.495665-04:00.jpg",
      "mtime": "1658866725",
      "size": "9585",
      "md5": "a8adb13a479db69ce24f0994caac9a07",
      "crc32": "0dfccb87",
      "sha1": "2367251f36d6f91f2eff3630bc06af7cd766d1b1"
    },
    {
      "name": "newrepublic-2022-07-26T22:42:26.702570-04:00.accessibility.json",
      "source": "original",
      "mtime": "1658889749",
      "size": "30285",
      "md5": "a017fc862740fb9945f7496cf9d3073a",
      "crc32": "6a9fce4e",
      "sha1": "e57dce7774ef1e5db14fa3e7d080ba8ab5b06c8a",
      "format": "JSON"
    },
    {
      "name": "newrepublic-2022-07-26T22:42:26.702570-04:00.hyperlinks.json",
      "source": "original",
      "mtime": "1658889751",
      "size": "23475",
      "md5": "b778a24ef9a5facbea4ca4cca53f7919",
      "crc32": "18b03cc8",
      "sha1": "d74c4d566d97cb667e2f9bfa64f0440f81a75e4a",
      "format": "JSON"
    },
    {
      "name": "newrepublic-2022-07-26T22:42:26.702570-04:00.jpg",
      "source": "original",
      "mtime": "1658889748",
      "size": "310950",
      "md5": "ecd21fa852bcc2d3be810ceef687bc56",
      "crc32": "c8905e80",
      "sha1": "f8d29e7d160f9f874a96f7750cf182068f3eb937",
      "format": "JPEG",
      "rotation": "0"
    },
    {
      "name": "newrepublic-2022-07-26T22:42:26.702570-04:00.lighthouse.json",
      "source": "original",
      "mtime": "1658889752",
      "size": "1467",
      "md5": "a10fa82e5eb079fb0682f51c92e59f21",
      "crc32": "45ac3926",
      "sha1": "0cdf2e6a198eca0d6c69f8494d02c4dbe6c3b0be",
      "format": "JSON"
    },
    {
      "name": "newrepublic-2022-07-26T22:42:26.702570-04:00_thumb.jpg",
      "source": "derivative",
      "format": "JPEG Thumb",
      "original": "newrepublic-2022-07-26T22:42:26.702570-04:00.jpg",
      "mtime": "1658892479",
      "size": "9768",
      "md5": "f72a4b2196e68bf00ae112cf9b58307c",
      "crc32": "aa6ec714",
      "sha1": "1efe2337127086c6bf9fa8d8b4cdde88713d41c2"
    },
    {
      "name": "newrepublic-2022-07-27T10:36:17.653763-04:00.accessibility.json",
      "source": "original",
      "mtime": "1658932580",
      "size": "30305",
      "md5": "15b002ff92d08c447ff87a956a9366b4",
      "crc32": "0012e37b",
      "sha1": "88a2f639075dc32273aacea43508f3c10876a517",
      "format": "JSON"
    },
    {
      "name": "newrepublic-2022-07-27T10:36:17.653763-04:00.hyperlinks.json",
      "source": "original",
      "mtime": "1658932582",
      "size": "23942",
      "md5": "19cfe05b5bd7e74bfa8706f4face554a",
      "crc32": "30881b7f",
      "sha1": "e6d8785448e4012134a00387bc18f3a9afc88d9b",
      "format": "JSON"
    },
    {
      "name": "newrepublic-2022-07-27T10:36:17.653763-04:00.jpg",
      "source": "original",
      "mtime": "1658932579",
      "size": "280681",
      "md5": "75deb8d48035926570bf5d839eec6a70",
      "crc32": "2d32a916",
      "sha1": "0e9334bf258317c3ec7f8b4328b92a88c2ab1f29",
      "format": "JPEG",
      "rotation": "0"
    },
    {
      "name": "newrepublic-2022-07-27T10:36:17.653763-04:00.lighthouse.json",
      "source": "original",
      "mtime": "1658932584",
      "size": "1468",
      "md5": "3d599502cc26b96d4d13a336aa7a292c",
      "crc32": "ed8cb9df",
      "sha1": "3b4959eb5fe2d43fb0c95083aac9d673f20fdd7e",
      "format": "JSON"
    },
    {
      "name": "newrepublic-2022-07-27T10:36:17.653763-04:00_thumb.jpg",
      "source": "derivative",
      "format": "JPEG Thumb",
      "original": "newrepublic-2022-07-27T10:36:17.653763-04:00.jpg",
      "mtime": "1658953122",
      "size": "9807",
      "md5": "8e220f94ce7fee9a3e78496c98a980ce",
      "crc32": "f744c9f8",
      "sha1": "e52d34b92892f7f3b2045bdaa3cc96c745158e59"
    },
    {
      "name": "newrepublic-2022-07-27T22:42:50.190067-04:00.accessibility.json",
      "source": "original",
      "mtime": "1658976173",
      "size": "31726",
      "md5": "77ddd6041cb8580c7abafa229bf08b73",
      "crc32": "41471a57",
      "sha1": "9151dced28c7e2f14ec25838860e1c5564a567ad",
      "format": "JSON"
    },
    {
      "name": "newrepublic-2022-07-27T22:42:50.190067-04:00.hyperlinks.json",
      "source": "original",
      "mtime": "1658976174",
      "size": "25385",
      "md5": "2522ce9d6d2ed883e41d26ae376a581b",
      "crc32": "9264e14d",
      "sha1": "1a7bca4149676d36bb32be31b9121a0844114611",
      "format": "JSON"
    },
    {
      "name": "newrepublic-2022-07-27T22:42:50.190067-04:00.jpg",
      "source": "original",
      "mtime": "1658976171",
      "size": "276272",
      "md5": "f7cb0581e3c27d9f2eb9272dca4e3960",
      "crc32": "814d4370",
      "sha1": "282eeeab231e9f83b97ede55085982adedbf4b61",
      "format": "JPEG",
      "rotation": "0"
    },
    {
      "name": "newrepublic-2022-07-27T22:42:50.190067-04:00.lighthouse.json",
      "source": "original",
      "mtime": "1658976176",
      "size": "1468",
      "md5": "8ad259adb6460c04dca2ac9edb295807",
      "crc32": "db1d7ccd",
      "sha1": "a045a97e4a53f8ddfa8ffbd9b7fe5d8201fec820",
      "format": "JSON"
    },
    {
      "name": "newrepublic-2022-07-27T22:42:50.190067-04:00_thumb.jpg",
      "source": "derivative",
      "format": "JPEG Thumb",
      "original": "newrepublic-2022-07-27T22:42:50.190067-04:00.jpg",
      "mtime": "1658985916",
      "size": "9866",
      "md5": "92f9da32130663594d8ed139afbad0c6",
      "crc32": "f9f00173",
      "sha1": "fbbaa185ab0bc6b443a64b92e8286fa4fc19d0cb"
    },
    {
      "name": "newrepublic-2022-07-28T11:46:48.740473-04:00.accessibility.json",
      "source": "original",
      "mtime": "1659023211",
      "size": "29954",
      "md5": "37de85f270cb56780c5bbc11c58f5688",
      "crc32": "04534d3d",
      "sha1": "74fa93e029bdc483dd7a74d16c6efd0ca7269a5c",
      "format": "JSON"
    },
    {
      "name": "newrepublic-2022-07-28T11:46:48.740473-04:00.hyperlinks.json",
      "source": "original",
      "mtime": "1659023213",
      "size": "23218",
      "md5": "5cae3f24e145371635711bf9215a2672",
      "crc32": "1cb649bf",
      "sha1": "f56c635f4307afad30544683080b35bff29bcecb",
      "format": "JSON"
    },
    {
      "name": "newrepublic-2022-07-28T11:46:48.740473-04:00.jpg",
      "source": "original",
      "mtime": "1659023209",
      "size": "319254",
      "md5": "e5df6ae6282bdd8c86f7ca4a1f5201b4",
      "crc32": "ec85dc5a",
      "sha1": "52df02b6f14276397d6643f594c5d3e60819174c",
      "format": "JPEG",
      "rotation": "0"
    },
    {
      "name": "newrepublic-2022-07-28T11:46:48.740473-04:00.lighthouse.json",
      "source": "original",
      "mtime": "1659023214",
      "size": "1468",
      "md5": "b084ab2266371ef8a9d870de8de3cd73",
      "crc32": "e520450c",
      "sha1": "76d00b5f1c64561c001a1fc5f04e2d9f70bdd3af",
      "format": "JSON"
    },
    {
      "name": "newrepublic-2022-07-28T11:46:48.740473-04:00_thumb.jpg",
      "source": "derivative",
      "format": "JPEG Thumb",
      "original": "newrepublic-2022-07-28T11:46:48.740473-04:00.jpg",
      "mtime": "1659033927",
      "size": "10381",
      "md5": "1cff2431ba546e09e3beb1a83d55a683",
      "crc32": "ab5b1b47",
      "sha1": "0936adcab9cd4e5d7f0aefe97146a2c02c9638e6"
    },
    {
      "name": "newrepublic-2022-07-28T14:44:46.188764-04:00.accessibility.json",
      "source": "original",
      "mtime": "1659033890",
      "size": "30501",
      "md5": "0da52ad0109050d0e3231404b04e2ef2",
      "crc32": "fe6b43c6",
      "sha1": "a38df124d05fda11c56c5ab4b0466edabdf09122",
      "format": "JSON"
    },
    {
      "name": "newrepublic-2022-07-28T14:44:46.188764-04:00.hyperlinks.json",
      "source": "original",
      "mtime": "1659033892",
      "size": "23716",
      "md5": "780a4b1460f81f232597473cdaadab14",
      "crc32": "f4cb9c31",
      "sha1": "15d62f54bded9ea5e19cca090c922c81c0ac3d03",
      "format": "JSON"
    },
    {
      "name": "newrepublic-2022-07-28T14:44:46.188764-04:00.jpg",
      "source": "original",
      "mtime": "1659033888",
      "size": "301641",
      "md5": "16c79148d60517d84ebc81709d727908",
      "crc32": "c7dd333e",
      "sha1": "826b1fa661543902826e1ee827d9dfec6f96611f",
      "format": "JPEG",
      "rotation": "0"
    },
    {
      "name": "newrepublic-2022-07-28T14:44:46.188764-04:00.lighthouse.json",
      "source": "original",
      "mtime": "1659033894",
      "size": "1468",
      "md5": "e2238fc5718ad27f194b7d1aab321022",
      "crc32": "cf6fb645",
      "sha1": "2249bc7bd223b418e30c3b27af655be10d854889",
      "format": "JSON"
    },
    {
      "name": "newrepublic-2022-07-28T14:44:46.188764-04:00_thumb.jpg",
      "source": "derivative",
      "format": "JPEG Thumb",
      "original": "newrepublic-2022-07-28T14:44:46.188764-04:00.jpg",
      "mtime": "1659056868",
      "size": "10150",
      "md5": "ad14daef05627c9201e42b7863e62cd4",
      "crc32": "8f246911",
      "sha1": "86b89206ecc8cf1a97ac9f6bae33edbf0af9082a"
    },
    {
      "name": "newrepublic-2022-07-28T22:40:59.333476-04:00.accessibility.json",
      "source": "original",
      "mtime": "1659062462",
      "size": "30551",
      "md5": "d830523d7017a3f4096e58f66a40c45a",
      "crc32": "d510700f",
      "sha1": "19ca4af4fb3f5dfe084838b099fd91e2b3d680e0",
      "format": "JSON"
    },
    {
      "name": "newrepublic-2022-07-28T22:40:59.333476-04:00.hyperlinks.json",
      "source": "original",
      "mtime": "1659062463",
      "size": "23646",
      "md5": "f55f07e9dc8521808c89043d6a8c633c",
      "crc32": "20991ac2",
      "sha1": "3c6384ba616c4f07498d09580cca0df9f4d61c99",
      "format": "JSON"
    },
    {
      "name": "newrepublic-2022-07-28T22:40:59.333476-04:00.jpg",
      "source": "original",
      "mtime": "1659062460",
      "size": "269026",
      "md5": "e9a155c6fc9daf4f534b7c7dfd04f725",
      "crc32": "a270a180",
      "sha1": "b17e49d6c2f48783c5c4152d8e079d270f316421",
      "format": "JPEG",
      "rotation": "0"
    },
    {
      "name": "newrepublic-2022-07-28T22:40:59.333476-04:00.lighthouse.json",
      "source": "original",
      "mtime": "1659062465",
      "size": "1467",
      "md5": "3346e6b710adc66b4a9f08fbb401c2c2",
      "crc32": "ef589dca",
      "sha1": "43525aed1461c36976aa59eec02a7cb794bb6308",
      "format": "JSON"
    },
    {
      "name": "newrepublic-2022-07-28T22:40:59.333476-04:00_thumb.jpg",
      "source": "derivative",
      "format": "JPEG Thumb",
      "original": "newrepublic-2022-07-28T22:40:59.333476-04:00.jpg",
      "mtime": "1659099487",
      "size": "9569",
      "md5": "59f56181d2a163310ed592458163a866",
      "crc32": "c82d4d1b",
      "sha1": "761fdccf90ae6d276448ae0e802b8d53475cb270"
    },
    {
      "name": "newrepublic-2022-07-29T10:45:17.570122-04:00.accessibility.json",
      "source": "original",
      "mtime": "1659105923",
      "size": "29543",
      "md5": "706d26852b17393dd85a06a867e733f1",
      "crc32": "48e85f7b",
      "sha1": "c18e19bfc90908f5a6b95a5c61612acdec8645d7",
      "format": "JSON"
    },
    {
      "name": "newrepublic-2022-07-29T10:45:17.570122-04:00.hyperlinks.json",
      "source": "original",
      "mtime": "1659105925",
      "size": "23116",
      "md5": "a4da4adf854a1e76837e73c885a7f72f",
      "crc32": "ea2c0e3c",
      "sha1": "2221ae1c55b284cf13af8cdf1249ecc077e7ad2c",
      "format": "JSON"
    },
    {
      "name": "newrepublic-2022-07-29T10:45:17.570122-04:00.jpg",
      "source": "original",
      "mtime": "1659105919",
      "size": "273221",
      "md5": "8d4beda1ff885d187d362752467e8499",
      "crc32": "f6a8bf7f",
      "sha1": "8593b7e2d8bed144c9ad94704766a6ac611009ab",
      "format": "JPEG",
      "rotation": "0"
    },
    {
      "name": "newrepublic-2022-07-29T10:45:17.570122-04:00.lighthouse.json",
      "source": "original",
      "mtime": "1659105927",
      "size": "1467",
      "md5": "5a709d1b49100e2f9fe81393e59a019d",
      "crc32": "792b8262",
      "sha1": "cb99ad605e6092252aa4b86fbf9c3ede53170097",
      "format": "JSON"
    },
    {
      "name": "newrepublic-2022-07-29T10:45:17.570122-04:00_thumb.jpg",
      "source": "derivative",
      "format": "JPEG Thumb",
      "original": "newrepublic-2022-07-29T10:45:17.570122-04:00.jpg",
      "mtime": "1659120000",
      "size": "9820",
      "md5": "4fc330e09a6dab2977ffc4ab66528dda",
      "crc32": "ae7836b7",
      "sha1": "3f22b0a6221c85d8b05a8da96f2b916525d62d40"
    },
    {
      "name": "newrepublic-2022-07-29T14:36:44.587308-04:00.accessibility.json",
      "source": "original",
      "mtime": "1659119808",
      "size": "30491",
      "md5": "5fa52127444ef90780b9e4487298d352",
      "crc32": "ea23cc51",
      "sha1": "fde2bb7a1d91bb75bae150e660dc22c8c7451028",
      "format": "JSON"
    },
    {
      "name": "newrepublic-2022-07-29T14:36:44.587308-04:00.hyperlinks.json",
      "source": "original",
      "mtime": "1659119809",
      "size": "23346",
      "md5": "27d5b8634aae92bf5be6a79eb4d17006",
      "crc32": "35e2bc75",
      "sha1": "0fc0f34d1f14826aa82f0ee1745e80a6f0a4e6a5",
      "format": "JSON"
    },
    {
      "name": "newrepublic-2022-07-29T14:36:44.587308-04:00.jpg",
      "source": "original",
      "mtime": "1659119806",
      "size": "273337",
      "md5": "813e4b6a6dacd5608c4f84f3c8ed8e75",
      "crc32": "ac0117dc",
      "sha1": "82b76049fd95b21174847ee96c2c64b2a9769755",
      "format": "JPEG",
      "rotation": "0"
    },
    {
      "name": "newrepublic-2022-07-29T14:36:44.587308-04:00.lighthouse.json",
      "source": "original",
      "mtime": "1659119811",
      "size": "1467",
      "md5": "ade17370dfddbf50f6f5a49954014f03",
      "crc32": "a72b12b7",
      "sha1": "379aa79706788a826fa06e689fa7a0c6d59591ae",
      "format": "JSON"
    },
    {
      "name": "newrepublic-2022-07-29T14:36:44.587308-04:00_thumb.jpg",
      "source": "derivative",
      "format": "JPEG Thumb",
      "original": "newrepublic-2022-07-29T14:36:44.587308-04:00.jpg",
      "mtime": "1659149187",
      "size": "9819",
      "md5": "ea1e60621db7b1a690594268a560fddf",
      "crc32": "bd7e6118",
      "sha1": "eb37db6bd3329681869e9edc1f8763a03f5264f1"
    },
    {
      "name": "newrepublic-2022-07-29T22:45:45.022236-04:00.accessibility.json",
      "source": "original",
      "mtime": "1659149148",
      "size": "29922",
      "md5": "e89779ddbe48a57453e700b8181d2720",
      "crc32": "9333a538",
      "sha1": "02d70ee80142e6158f28211bac879c253822d229",
      "format": "JSON"
    },
    {
      "name": "newrepublic-2022-07-29T22:45:45.022236-04:00.hyperlinks.json",
      "source": "original",
      "mtime": "1659149149",
      "size": "23383",
      "md5": "fde85701a1cf2cf2ea0dc29ff431b20c",
      "crc32": "4751691d",
      "sha1": "a35113d280844689c4493c106915a3072a08ff14",
      "format": "JSON"
    },
    {
      "name": "newrepublic-2022-07-29T22:45:45.022236-04:00.jpg",
      "source": "original",
      "mtime": "1659149146",
      "size": "277443",
      "md5": "6b09134540b4852dc521a6743ade089e",
      "crc32": "2db64e47",
      "sha1": "dd0607c2a6620fb931e26fca1956b9404e52cc5a",
      "format": "JPEG",
      "rotation": "0"
    },
    {
      "name": "newrepublic-2022-07-29T22:45:45.022236-04:00.lighthouse.json",
      "source": "original",
      "mtime": "1659149151",
      "size": "1467",
      "md5": "e4340534d31d72cae17c3d7e8eef0cd7",
      "crc32": "83e959a2",
      "sha1": "fc94a5b924691e7c96fcd0f1e34946d7decafbec",
      "format": "JSON"
    },
    {
      "name": "newrepublic-2022-07-29T22:45:45.022236-04:00_thumb.jpg",
      "source": "derivative",
      "format": "JPEG Thumb",
      "original": "newrepublic-2022-07-29T22:45:45.022236-04:00.jpg",
      "mtime": "1659195961",
      "size": "10065",
      "md5": "2a3155e5241b9b7a9d91308b4ca89681",
      "crc32": "f8c37257",
      "sha1": "4fa1debfac5c3f27d027692ba1a4b46712ee31b5"
    },
    {
      "name": "newrepublic-2022-07-30T11:45:19.715715-04:00.accessibility.json",
      "source": "original",
      "mtime": "1659195922",
      "size": "29920",
      "md5": "2945b0ab894afc0e816f304a763b2782",
      "crc32": "bd55b53e",
      "sha1": "d7279d8edb1e90012ba3a37ae3d3a9248e20b616",
      "format": "JSON"
    },
    {
      "name": "newrepublic-2022-07-30T11:45:19.715715-04:00.hyperlinks.json",
      "source": "original",
      "mtime": "1659195923",
      "size": "23383",
      "md5": "fde85701a1cf2cf2ea0dc29ff431b20c",
      "crc32": "4751691d",
      "sha1": "a35113d280844689c4493c106915a3072a08ff14",
      "format": "JSON"
    },
    {
      "name": "newrepublic-2022-07-30T11:45:19.715715-04:00.jpg",
      "source": "original",
      "mtime": "1659195920",
      "size": "277844",
      "md5": "bd66393cc1fb7620d44a2717eec8bdd8",
      "crc32": "9694879c",
      "sha1": "98e27bb9c86ed3c08a9825c555b842d558f4112e",
      "format": "JPEG",
      "rotation": "0"
    },
    {
      "name": "newrepublic-2022-07-30T11:45:19.715715-04:00.lighthouse.json",
      "source": "original",
      "mtime": "1659195930",
      "size": "1468",
      "md5": "dbda793fe408971a3dcb40535138de1e",
      "crc32": "f4fe0b70",
      "sha1": "49bfdb381d9176c1aa26caac5618b89998821a68",
      "format": "JSON"
    },
    {
      "name": "newrepublic-2022-07-30T11:45:19.715715-04:00_thumb.jpg",
      "source": "derivative",
      "format": "JPEG Thumb",
      "original": "newrepublic-2022-07-30T11:45:19.715715-04:00.jpg",
      "mtime": "1659206568",
      "size": "10033",
      "md5": "61cc5a90bc6bd34a47ee72aab61ff844",
      "crc32": "0037bf56",
      "sha1": "6725ac195604bf656c350beeb27541407a2401b6"
    },
    {
      "name": "newrepublic-2022-07-30T14:40:34.115185-04:00.accessibility.json",
      "source": "original",
      "mtime": "1659206437",
      "size": "29842",
      "md5": "645ff3f64fc7c41e358f0bfe413817ee",
      "crc32": "5ce0a4aa",
      "sha1": "148a61e94e6d7d37611217f4cdb8472cde6a457f",
      "format": "JSON"
    },
    {
      "name": "newrepublic-2022-07-30T14:40:34.115185-04:00.hyperlinks.json",
      "source": "original",
      "mtime": "1659206439",
      "size": "23383",
      "md5": "fde85701a1cf2cf2ea0dc29ff431b20c",
      "crc32": "4751691d",
      "sha1": "a35113d280844689c4493c106915a3072a08ff14",
      "format": "JSON"
    },
    {
      "name": "newrepublic-2022-07-30T14:40:34.115185-04:00.jpg",
      "source": "original",
      "mtime": "1659206436",
      "size": "277844",
      "md5": "bd66393cc1fb7620d44a2717eec8bdd8",
      "crc32": "9694879c",
      "sha1": "98e27bb9c86ed3c08a9825c555b842d558f4112e",
      "format": "JPEG",
      "rotation": "0"
    },
    {
      "name": "newrepublic-2022-07-30T14:40:34.115185-04:00.lighthouse.json",
      "source": "original",
      "mtime": "1659206441",
      "size": "1468",
      "md5": "d90e9bb1997316042ea07d78c1436cd9",
      "crc32": "f3027d4d",
      "sha1": "7ae991f767b45cfca2cd94c7f9f45c24710057a2",
      "format": "JSON"
    },
    {
      "name": "newrepublic-2022-07-30T14:40:34.115185-04:00_thumb.jpg",
      "source": "derivative",
      "format": "JPEG Thumb",
      "original": "newrepublic-2022-07-30T14:40:34.115185-04:00.jpg",
      "mtime": "1659236656",
      "size": "10033",
      "md5": "61cc5a90bc6bd34a47ee72aab61ff844",
      "crc32": "0037bf56",
      "sha1": "6725ac195604bf656c350beeb27541407a2401b6"
    },
    {
      "name": "newrepublic-2022-07-30T23:02:42.715229-04:00.accessibility.json",
      "source": "original",
      "mtime": "1659236565",
      "size": "29922",
      "md5": "e89779ddbe48a57453e700b8181d2720",
      "crc32": "9333a538",
      "sha1": "02d70ee80142e6158f28211bac879c253822d229",
      "format": "JSON"
    },
    {
      "name": "newrepublic-2022-07-30T23:02:42.715229-04:00.hyperlinks.json",
      "source": "original",
      "mtime": "1659236566",
      "size": "23383",
      "md5": "fde85701a1cf2cf2ea0dc29ff431b20c",
      "crc32": "4751691d",
      "sha1": "a35113d280844689c4493c106915a3072a08ff14",
      "format": "JSON"
    },
    {
      "name": "newrepublic-2022-07-30T23:02:42.715229-04:00.jpg",
      "source": "original",
      "mtime": "1659236564",
      "size": "277443",
      "md5": "6b09134540b4852dc521a6743ade089e",
      "crc32": "2db64e47",
      "sha1": "dd0607c2a6620fb931e26fca1956b9404e52cc5a",
      "format": "JPEG",
      "rotation": "0"
    },
    {
      "name": "newrepublic-2022-07-30T23:02:42.715229-04:00.lighthouse.json",
      "source": "original",
      "mtime": "1659236568",
      "size": "1468",
      "md5": "e346617f59a19be15f1abe395fa14db1",
      "crc32": "e90bb3e2",
      "sha1": "7434a0b8b55b02b5750e35b24b1e20b19d97452c",
      "format": "JSON"
    },
    {
      "name": "newrepublic-2022-07-30T23:02:42.715229-04:00_thumb.jpg",
      "source": "derivative",
      "format": "JPEG Thumb",
      "original": "newrepublic-2022-07-30T23:02:42.715229-04:00.jpg",
      "mtime": "1659261374",
      "size": "10065",
      "md5": "2a3155e5241b9b7a9d91308b4ca89681",
      "crc32": "f8c37257",
      "sha1": "4fa1debfac5c3f27d027692ba1a4b46712ee31b5"
    },
    {
      "name": "newrepublic-2022-07-31T10:42:52.302492-04:00.accessibility.json",
      "source": "original",
      "mtime": "1659278574",
      "size": "29836",
      "md5": "8e8c7b59e7129118c2c8cbd04f679c24",
      "crc32": "f207072c",
      "sha1": "83f1fddfebbac98e3ad0523b8618a2ff00528382",
      "format": "JSON"
    },
    {
      "name": "newrepublic-2022-07-31T10:42:52.302492-04:00.hyperlinks.json",
      "source": "original",
      "mtime": "1659278576",
      "size": "23101",
      "md5": "5aa527b6bb044d7acd04eba90f71bbd1",
      "crc32": "d15e91cc",
      "sha1": "d85f89703e8f9e9c154ad23d5265a8d47ff87564",
      "format": "JSON"
    },
    {
      "name": "newrepublic-2022-07-31T10:42:52.302492-04:00.jpg",
      "source": "original",
      "mtime": "1659278573",
      "size": "277386",
      "md5": "1a077b4e56b3754f4395687a960e9482",
      "crc32": "07b3259b",
      "sha1": "fe1988a56069490e969fc4991958c7ab38a7c6d4",
      "format": "JPEG",
      "rotation": "0"
    },
    {
      "name": "newrepublic-2022-07-31T10:42:52.302492-04:00.lighthouse.json",
      "source": "original",
      "mtime": "1659278577",
      "size": "1468",
      "md5": "42f68e098f5c9eb94ba3fd9d4c4dd559",
      "crc32": "44ffa9dd",
      "sha1": "ee0104d3abcdadbe280dcf15a1e3536283e76015",
      "format": "JSON"
    },
    {
      "name": "newrepublic-2022-07-31T10:42:52.302492-04:00_thumb.jpg",
      "source": "derivative",
      "format": "JPEG Thumb",
      "original": "newrepublic-2022-07-31T10:42:52.302492-04:00.jpg",
      "mtime": "1659282428",
      "size": "10071",
      "md5": "412e468a7190f9afc16942693c69a10a",
      "crc32": "17335afa",
      "sha1": "fa1f337fff884ee7a1dafe5b2cce6d9a484d7978"
    },
    {
      "name": "newrepublic-2022-07-31T14:36:57.547628-04:00.accessibility.json",
      "source": "original",
      "mtime": "1659292620",
      "size": "29834",
      "md5": "c4d24e22c739e52d5958d5481fa4656c",
      "crc32": "1dff982b",
      "sha1": "2e257bec23aed2c501359a2ae00a1603142efa8c",
      "format": "JSON"
    },
    {
      "name": "newrepublic-2022-07-31T14:36:57.547628-04:00.hyperlinks.json",
      "source": "original",
      "mtime": "1659292622",
      "size": "23351",
      "md5": "1a5a7d05d8204345fb27085f75e9d4b9",
      "crc32": "9c10a501",
      "sha1": "635b6c4c6c0190d1a8e2d0b2b1f7600cec0dc787",
      "format": "JSON"
    },
    {
      "name": "newrepublic-2022-07-31T14:36:57.547628-04:00.jpg",
      "source": "original",
      "mtime": "1659292619",
      "size": "277386",
      "md5": "1a077b4e56b3754f4395687a960e9482",
      "crc32": "07b3259b",
      "sha1": "fe1988a56069490e969fc4991958c7ab38a7c6d4",
      "format": "JPEG",
      "rotation": "0"
    },
    {
      "name": "newrepublic-2022-07-31T14:36:57.547628-04:00.lighthouse.json",
      "source": "original",
      "mtime": "1659292623",
      "size": "1467",
      "md5": "8a773e71d129bb766f7cc4d9599297c8",
      "crc32": "c2efb796",
      "sha1": "8b10fb8de1039b74a2d614a588f87f5edebbce22",
      "format": "JSON"
    },
    {
      "name": "newrepublic-2022-07-31T14:36:57.547628-04:00_thumb.jpg",
      "source": "derivative",
      "format": "JPEG Thumb",
      "original": "newrepublic-2022-07-31T14:36:57.547628-04:00.jpg",
      "mtime": "1659292950",
      "size": "10071",
      "md5": "412e468a7190f9afc16942693c69a10a",
      "crc32": "17335afa",
      "sha1": "fa1f337fff884ee7a1dafe5b2cce6d9a484d7978"
    },
    {
      "name": "newrepublic-2022-07-31T22:41:31.871712-04:00.accessibility.json",
      "source": "original",
      "mtime": "1659321694",
      "size": "29298",
      "md5": "82e7c3f883a931a504423a0e2f9d79b5",
      "crc32": "c0040de7",
      "sha1": "3f7f71386eee8b6799f075e6899eb71885cdb43e",
      "format": "JSON"
    },
    {
      "name": "newrepublic-2022-07-31T22:41:31.871712-04:00.hyperlinks.json",
      "source": "original",
      "mtime": "1659321696",
      "size": "23101",
      "md5": "5aa527b6bb044d7acd04eba90f71bbd1",
      "crc32": "d15e91cc",
      "sha1": "d85f89703e8f9e9c154ad23d5265a8d47ff87564",
      "format": "JSON"
    },
    {
      "name": "newrepublic-2022-07-31T22:41:31.871712-04:00.jpg",
      "source": "original",
      "mtime": "1659321692",
      "size": "277386",
      "md5": "1a077b4e56b3754f4395687a960e9482",
      "crc32": "07b3259b",
      "sha1": "fe1988a56069490e969fc4991958c7ab38a7c6d4",
      "format": "JPEG",
      "rotation": "0"
    },
    {
      "name": "newrepublic-2022-07-31T22:41:31.871712-04:00.lighthouse.json",
      "source": "original",
      "mtime": "1659321697",
      "size": "1468",
      "md5": "c8b8ff801dc2f304827092a8d5252b8b",
      "crc32": "900ef134",
      "sha1": "35f7e1e64356f4bc6ae4164edd3ca0bb46bc75fa",
      "format": "JSON"
    },
    {
      "name": "newrepublic-2022-07-31T22:41:31.871712-04:00_thumb.jpg",
      "source": "derivative",
      "format": "JPEG Thumb",
      "original": "newrepublic-2022-07-31T22:41:31.871712-04:00.jpg",
      "mtime": "1659322116",
      "size": "10071",
      "md5": "412e468a7190f9afc16942693c69a10a",
      "crc32": "17335afa",
      "sha1": "fa1f337fff884ee7a1dafe5b2cce6d9a484d7978"
    },
    {
      "name": "newrepublic-2022-08-01T11:05:19.244293-04:00.accessibility.json",
      "source": "original",
      "mtime": "1659366322",
      "size": "29884",
      "md5": "4a391f4d71e8621daa582384fd41e6c5",
      "crc32": "59158ba2",
      "sha1": "6abac6dc8917975426d5af4d3167b158683a51bc",
      "format": "JSON"
    },
    {
      "name": "newrepublic-2022-08-01T11:05:19.244293-04:00.hyperlinks.json",
      "source": "original",
      "mtime": "1659366324",
      "size": "23282",
      "md5": "92d563dc7545c72d2b4a92e8f77ec901",
      "crc32": "40ade5f1",
      "sha1": "8a5286ccbf70057b25df079d1bb365def3a9921a",
      "format": "JSON"
    },
    {
      "name": "newrepublic-2022-08-01T11:05:19.244293-04:00.jpg",
      "source": "original",
      "mtime": "1659366321",
      "size": "319417",
      "md5": "67e8fe89d0da1115a0ad7ee4697b5bee",
      "crc32": "3f841769",
      "sha1": "409eaa876ab01c65de4dc2d27c0821851e63fd81",
      "format": "JPEG",
      "rotation": "0"
    },
    {
      "name": "newrepublic-2022-08-01T11:05:19.244293-04:00.lighthouse.json",
      "source": "original",
      "mtime": "1659366326",
      "size": "1468",
      "md5": "daf9dd8aa4de93b85e9e9c112ecf7e24",
      "crc32": "683075a2",
      "sha1": "0a899d6e9c84f92ad81081c226f91be78da77dd4",
      "format": "JSON"
    },
    {
      "name": "newrepublic-2022-08-01T11:05:19.244293-04:00_thumb.jpg",
      "source": "derivative",
      "format": "JPEG Thumb",
      "original": "newrepublic-2022-08-01T11:05:19.244293-04:00.jpg",
      "mtime": "1659372187",
      "size": "10219",
      "md5": "c1281422c235a54b9acbc455f41b9153",
      "crc32": "160344b7",
      "sha1": "9be2820484a57b4e3f5ec8322ac07d8d0aa74a85"
    },
    {
      "name": "newrepublic-2022-08-01T14:41:28.115514-04:00.accessibility.json",
      "source": "original",
      "mtime": "1659379290",
      "size": "30005",
      "md5": "e4ce9aeaed50f270534cbb819308d1b7",
      "crc32": "348678f0",
      "sha1": "2303de83dd0e252d2885da5afc527785fd15be02",
      "format": "JSON"
    },
    {
      "name": "newrepublic-2022-08-01T14:41:28.115514-04:00.hyperlinks.json",
      "source": "original",
      "mtime": "1659379292",
      "size": "23489",
      "md5": "8da6be8ac861fc1d6188e59d0203a2ae",
      "crc32": "83bc20fb",
      "sha1": "5c37468a5706d088ea1930fa3e6ce72b30800eb3",
      "format": "JSON"
    },
    {
      "name": "newrepublic-2022-08-01T14:41:28.115514-04:00.jpg",
      "source": "original",
      "mtime": "1659379289",
      "size": "309961",
      "md5": "4700c0376a6d14e3901fd7003d5fba5b",
      "crc32": "3f8e45e0",
      "sha1": "a3cdc99e73c9695fd941231076ce3d4b5a8576d2",
      "format": "JPEG",
      "rotation": "0"
    },
    {
      "name": "newrepublic-2022-08-01T14:41:28.115514-04:00.lighthouse.json",
      "source": "original",
      "mtime": "1659379293",
      "size": "1468",
      "md5": "63643c8c886dcc76efc97a0f120e749f",
      "crc32": "87a315b0",
      "sha1": "fc38e407dc5bcefc78ae7681a2b470f74ec38972",
      "format": "JSON"
    },
    {
      "name": "newrepublic-2022-08-01T14:41:28.115514-04:00_thumb.jpg",
      "source": "derivative",
      "format": "JPEG Thumb",
      "original": "newrepublic-2022-08-01T14:41:28.115514-04:00.jpg",
      "mtime": "1659383196",
      "size": "9911",
      "md5": "6a50d2fa8f39180f257de8ff62cd46fc",
      "crc32": "5e98a9dd",
      "sha1": "430e07f642daf7aba6c49da5bdc2dc199aede8cd"
    },
    {
      "name": "newrepublic-2022-08-01T23:22:33.722928-04:00.accessibility.json",
      "source": "original",
      "mtime": "1659410557",
      "size": "29371",
      "md5": "80715d17587f4254cd6e8e6e3975a3bc",
      "crc32": "6de5e4a9",
      "sha1": "7d54ab7ce1216f4fbac38bfa9d4cea5b9f4d4421",
      "format": "JSON"
    },
    {
      "name": "newrepublic-2022-08-01T23:22:33.722928-04:00.hyperlinks.json",
      "source": "original",
      "mtime": "1659410559",
      "size": "23509",
      "md5": "a6ea4780bf15365144ba76e2d43be5cf",
      "crc32": "1c913a68",
      "sha1": "33416a5c8ab1c74f4ffac70ba088facf8180ec89",
      "format": "JSON"
    },
    {
      "name": "newrepublic-2022-08-01T23:22:33.722928-04:00.jpg",
      "source": "original",
      "mtime": "1659410555",
      "size": "309961",
      "md5": "4700c0376a6d14e3901fd7003d5fba5b",
      "crc32": "3f8e45e0",
      "sha1": "a3cdc99e73c9695fd941231076ce3d4b5a8576d2",
      "format": "JPEG",
      "rotation": "0"
    },
    {
      "name": "newrepublic-2022-08-01T23:22:33.722928-04:00.lighthouse.json",
      "source": "original",
      "mtime": "1659410560",
      "size": "1467",
      "md5": "93b027b895396b3fe898d50f3a1857d1",
      "crc32": "f36c4b25",
      "sha1": "011edf78303f6624f82eae334b1e5fe976b447b0",
      "format": "JSON"
    },
    {
      "name": "newrepublic-2022-08-01T23:22:33.722928-04:00_thumb.jpg",
      "source": "derivative",
      "format": "JPEG Thumb",
      "original": "newrepublic-2022-08-01T23:22:33.722928-04:00.jpg",
      "mtime": "1659413622",
      "size": "9911",
      "md5": "6a50d2fa8f39180f257de8ff62cd46fc",
      "crc32": "5e98a9dd",
      "sha1": "430e07f642daf7aba6c49da5bdc2dc199aede8cd"
    },
    {
      "name": "newrepublic-2022-08-02T11:00:11.551702-04:00.accessibility.json",
      "source": "original",
      "mtime": "1659452415",
      "size": "31245",
      "md5": "79e06c5dfaa6ba0fee2e1049cd2b26b9",
      "crc32": "cfe023ec",
      "sha1": "1ecb56b5f27b64ece4bf514a5015fed08a85e5e8",
      "format": "JSON"
    },
    {
      "name": "newrepublic-2022-08-02T11:00:11.551702-04:00.hyperlinks.json",
      "source": "original",
      "mtime": "1659452417",
      "size": "23881",
      "md5": "1e2b3152c9e46ce12c9738a35ec62e31",
      "crc32": "8da738c8",
      "sha1": "98062f1e822b9aef4b4ca10584f2a332afe3db59",
      "format": "JSON"
    },
    {
      "name": "newrepublic-2022-08-02T11:00:11.551702-04:00.jpg",
      "source": "original",
      "mtime": "1659452413",
      "size": "282847",
      "md5": "60420e36c377135ba275a4678299c206",
      "crc32": "42fccce3",
      "sha1": "c8dfed20519c163c7db567ffb31438b2b663f3b8",
      "format": "JPEG",
      "rotation": "0"
    },
    {
      "name": "newrepublic-2022-08-02T11:00:11.551702-04:00.lighthouse.json",
      "source": "original",
      "mtime": "1659452418",
      "size": "1468",
      "md5": "e23294f50268c2c6bd3995cec484e937",
      "crc32": "7a5dce7b",
      "sha1": "5d283e0fd5a2de250050ace86272c846021a8585",
      "format": "JSON"
    },
    {
      "name": "newrepublic-2022-08-02T11:00:11.551702-04:00_thumb.jpg",
      "source": "derivative",
      "format": "JPEG Thumb",
      "original": "newrepublic-2022-08-02T11:00:11.551702-04:00.jpg",
      "mtime": "1659465662",
      "size": "10033",
      "md5": "91a29f665d17ee54ecb6cd2981ce33a6",
      "crc32": "937fe25c",
      "sha1": "acfc13c3e3537e07e9720fdd6d24b2e00a7f1ac3"
    },
    {
      "name": "newrepublic-2022-08-02T14:39:25.138930-04:00.accessibility.json",
      "source": "original",
      "mtime": "1659465569",
      "size": "30577",
      "md5": "f9cfb3a34da88c891c10947498bcb5fb",
      "crc32": "789bebff",
      "sha1": "d205f81ee3cefbf837559298a1f2667f2c6ee48f",
      "format": "JSON"
    },
    {
      "name": "newrepublic-2022-08-02T14:39:25.138930-04:00.hyperlinks.json",
      "source": "original",
      "mtime": "1659465571",
      "size": "23552",
      "md5": "10ab91562ace1bdf72d8d599bb2b44c2",
      "crc32": "12872ed4",
      "sha1": "0ee767a056e1cbd0fe4401798cbc0ad34a47803f",
      "format": "JSON"
    },
    {
      "name": "newrepublic-2022-08-02T14:39:25.138930-04:00.jpg",
      "source": "original",
      "mtime": "1659465567",
      "size": "285910",
      "md5": "a79f4adbc81777a297b6d97684eaf290",
      "crc32": "70686353",
      "sha1": "2dd7c447375309349ddf66f81bcb9cf635f3b48d",
      "format": "JPEG",
      "rotation": "0"
    },
    {
      "name": "newrepublic-2022-08-02T14:39:25.138930-04:00.lighthouse.json",
      "source": "original",
      "mtime": "1659465572",
      "size": "1468",
      "md5": "c8811809f19528e2407a89136369fb33",
      "crc32": "42196bdb",
      "sha1": "948711c779e14bff0d89005a5c717d93114dc084",
      "format": "JSON"
    },
    {
      "name": "newrepublic-2022-08-02T14:39:25.138930-04:00_thumb.jpg",
      "source": "derivative",
      "format": "JPEG Thumb",
      "original": "newrepublic-2022-08-02T14:39:25.138930-04:00.jpg",
      "mtime": "1659482725",
      "size": "9584",
      "md5": "1665d31728c67f7c00cbbeaade797c30",
      "crc32": "0e361d59",
      "sha1": "0896d536fbf5b7f4859e7114ff05039ebe3e9a14"
    },
    {
      "name": "newrepublic-2022-08-03T00:37:17.614874-04:00.accessibility.json",
      "source": "original",
      "mtime": "1659501441",
      "size": "30701",
      "md5": "7812b233a1f59aa77ad936c19fcaf922",
      "crc32": "af84ca59",
      "sha1": "4f9bd092ba200d3e05b3f9d2317bc5cc801848c5",
      "format": "JSON"
    },
    {
      "name": "newrepublic-2022-08-03T00:37:17.614874-04:00.hyperlinks.json",
      "source": "original",
      "mtime": "1659501442",
      "size": "23707",
      "md5": "c3b9da1fb4d870023e90a72c317685ca",
      "crc32": "476cec69",
      "sha1": "c019e756e0a69215cca569eb441fc9819d5387b8",
      "format": "JSON"
    },
    {
      "name": "newrepublic-2022-08-03T00:37:17.614874-04:00.jpg",
      "source": "original",
      "mtime": "1659501439",
      "size": "292954",
      "md5": "f385c1035cc37deff825c1c762d2b4e1",
      "crc32": "6046fe9f",
      "sha1": "49584aa1e3c77e044ac2ee4360b8847c9118f094",
      "format": "JPEG",
      "rotation": "0"
    },
    {
      "name": "newrepublic-2022-08-03T00:37:17.614874-04:00.lighthouse.json",
      "source": "original",
      "mtime": "1659501444",
      "size": "1468",
      "md5": "b275ba9e3660a4ce03dca8af2c067177",
      "crc32": "f876830b",
      "sha1": "0001798532d0499ef9fb23a736550f1130abea98",
      "format": "JSON"
    },
    {
      "name": "newrepublic-2022-08-03T00:37:17.614874-04:00_thumb.jpg",
      "source": "derivative",
      "format": "JPEG Thumb",
      "original": "newrepublic-2022-08-03T00:37:17.614874-04:00.jpg",
      "mtime": "1659509923",
      "size": "9590",
      "md5": "8dd33507d0f0dbfe3f0d92dc87b1d3ef",
      "crc32": "23124943",
      "sha1": "6cf802d65411b1ba5d3ab32ac08b09e861d1218d"
    },
    {
      "name": "newrepublic-2022-08-03T13:04:06.600573-04:00.accessibility.json",
      "source": "original",
      "mtime": "1659546250",
      "size": "30591",
      "md5": "012888eb68d88ad9001fd9236e2b100c",
      "crc32": "712e35ba",
      "sha1": "4ae06edb71cdecd8a22ab8208306687de6feac48",
      "format": "JSON"
    },
    {
      "name": "newrepublic-2022-08-03T13:04:06.600573-04:00.hyperlinks.json",
      "source": "original",
      "mtime": "1659546252",
      "size": "23518",
      "md5": "b68a69a51d60990032fe07537a4eea07",
      "crc32": "899580ee",
      "sha1": "89c002c65f31cd89418431baa6942688d697286c",
      "format": "JSON"
    },
    {
      "name": "newrepublic-2022-08-03T13:04:06.600573-04:00.jpg",
      "source": "original",
      "mtime": "1659546248",
      "size": "277672",
      "md5": "2d4ecca8af8b3b45d73d18cac530f4e0",
      "crc32": "739fb094",
      "sha1": "198e3e3aa3be64da67e9e86d5e2a2584c732336f",
      "format": "JPEG",
      "rotation": "0"
    },
    {
      "name": "newrepublic-2022-08-03T13:04:06.600573-04:00.lighthouse.json",
      "source": "original",
      "mtime": "1659546254",
      "size": "1468",
      "md5": "c6cc493b0186b98532a12ab042a562db",
      "crc32": "7add9edb",
      "sha1": "66a5d419c162e1af702803e8c9056652dd88d281",
      "format": "JSON"
    },
    {
      "name": "newrepublic-2022-08-03T13:04:06.600573-04:00_thumb.jpg",
      "source": "derivative",
      "format": "JPEG Thumb",
      "original": "newrepublic-2022-08-03T13:04:06.600573-04:00.jpg",
      "mtime": "1659547462",
      "size": "9857",
      "md5": "88df1ba88da112f568444e2d9445dbe2",
      "crc32": "8d3892c0",
      "sha1": "7caef051be0b09ec4b3c7c3b0ede6198d05999dd"
    },
    {
      "name": "newrepublic-2022-08-03T14:41:36.812947-04:00.accessibility.json",
      "source": "original",
      "mtime": "1659552099",
      "size": "30517",
      "md5": "e87429543ce8254007c9df28dff1b7d1",
      "crc32": "7e1038ab",
      "sha1": "fe955730e5cd387725988568bfdc5c57a6a19e04",
      "format": "JSON"
    },
    {
      "name": "newrepublic-2022-08-03T14:41:36.812947-04:00.hyperlinks.json",
      "source": "original",
      "mtime": "1659552100",
      "size": "23216",
      "md5": "09bc8201e362059127272c3992921deb",
      "crc32": "20394f02",
      "sha1": "44b4ffebe6165e44245670a0c4dbff5973dc1ff3",
      "format": "JSON"
    },
    {
      "name": "newrepublic-2022-08-03T14:41:36.812947-04:00.jpg",
      "source": "original",
      "mtime": "1659552097",
      "size": "277672",
      "md5": "2d4ecca8af8b3b45d73d18cac530f4e0",
      "crc32": "739fb094",
      "sha1": "198e3e3aa3be64da67e9e86d5e2a2584c732336f",
      "format": "JPEG",
      "rotation": "0"
    },
    {
      "name": "newrepublic-2022-08-03T14:41:36.812947-04:00.lighthouse.json",
      "source": "original",
      "mtime": "1659552102",
      "size": "1468",
      "md5": "1cd29927a8dc188032aecc0f037db75c",
      "crc32": "c3c827c7",
      "sha1": "b35fd6b3e0b83dee9063dfb46828f158df08036c",
      "format": "JSON"
    },
    {
      "name": "newrepublic-2022-08-03T14:41:36.812947-04:00_thumb.jpg",
      "source": "derivative",
      "format": "JPEG Thumb",
      "original": "newrepublic-2022-08-03T14:41:36.812947-04:00.jpg",
      "mtime": "1659552799",
      "size": "9857",
      "md5": "88df1ba88da112f568444e2d9445dbe2",
      "crc32": "8d3892c0",
      "sha1": "7caef051be0b09ec4b3c7c3b0ede6198d05999dd"
    },
    {
      "name": "newrepublic-2022-08-03T23:28:32.474377-04:00.accessibility.json",
      "source": "original",
      "mtime": "1659583716",
      "size": "30368",
      "md5": "f6034d8bc3939c3e56f2f5c6eca1c985",
      "crc32": "215ee3b3",
      "sha1": "5ec8c215f54d2201f96341ddcd01916b1681e572",
      "format": "JSON"
    },
    {
      "name": "newrepublic-2022-08-03T23:28:32.474377-04:00.hyperlinks.json",
      "source": "original",
      "mtime": "1659583717",
      "size": "23442",
      "md5": "61356aeb85c9a5990aa2e0de1054b17c",
      "crc32": "4f4df3fa",
      "sha1": "cd9eafba2b8f059662c832f1a1a11e2caaca8dd4",
      "format": "JSON"
    },
    {
      "name": "newrepublic-2022-08-03T23:28:32.474377-04:00.jpg",
      "source": "original",
      "mtime": "1659583714",
      "size": "271289",
      "md5": "e6165906e6e7b543d9ef777e9b221c5b",
      "crc32": "f915271d",
      "sha1": "5c83f2014078a90e32ef0122d364a643f80f10d9",
      "format": "JPEG",
      "rotation": "0"
    },
    {
      "name": "newrepublic-2022-08-03T23:28:32.474377-04:00.lighthouse.json",
      "source": "original",
      "mtime": "1659583719",
      "size": "1468",
      "md5": "d4cd217070731674453f334653146d9b",
      "crc32": "7e5a35b6",
      "sha1": "5368bf297bd5bf266b9ab3415f52489ca0e4030d",
      "format": "JSON"
    },
    {
      "name": "newrepublic-2022-08-03T23:28:32.474377-04:00_thumb.jpg",
      "source": "derivative",
      "format": "JPEG Thumb",
      "original": "newrepublic-2022-08-03T23:28:32.474377-04:00.jpg",
      "mtime": "1659583771",
      "size": "9768",
      "md5": "6aa7c0d432b3ef3e1793f004b7c4b649",
      "crc32": "75eca45e",
      "sha1": "d3b6650cf79ae6b1dbe48db4c68d8e796e62fc59"
    },
    {
      "name": "newrepublic-2022-08-04T11:30:33.127755-04:00.accessibility.json",
      "source": "original",
      "mtime": "1659627036",
      "size": "30915",
      "md5": "6f405590800a9c414e65f8bed39dcdcf",
      "crc32": "83e73968",
      "sha1": "0f74c91d24b7540c540eecb9fac08c3530bd41e8",
      "format": "JSON"
    },
    {
      "name": "newrepublic-2022-08-04T11:30:33.127755-04:00.hyperlinks.json",
      "source": "original",
      "mtime": "1659627038",
      "size": "23185",
      "md5": "e4c411c3450eab2d3269e55dd8b0f5d0",
      "crc32": "b31b500e",
      "sha1": "84ea21a56e140f05079c35cf269f078c620f279e",
      "format": "JSON"
    },
    {
      "name": "newrepublic-2022-08-04T11:30:33.127755-04:00.jpg",
      "source": "original",
      "mtime": "1659627034",
      "size": "246046",
      "md5": "cffb893beb798f3d4c4cbd8d2510c384",
      "crc32": "48b0cdc4",
      "sha1": "7c0e4bec0c85faa8a2bf2e4c1d5045854cdf7a32",
      "format": "JPEG",
      "rotation": "0"
    },
    {
      "name": "newrepublic-2022-08-04T11:30:33.127755-04:00.lighthouse.json",
      "source": "original",
      "mtime": "1659627040",
      "size": "1468",
      "md5": "74e6ffe3d14844876a25ad3e002476f3",
      "crc32": "cd3651c7",
      "sha1": "dac44c01e95a490c9aa6617eec6948178acebffe",
      "format": "JSON"
    },
    {
      "name": "newrepublic-2022-08-04T11:30:33.127755-04:00_thumb.jpg",
      "source": "derivative",
      "format": "JPEG Thumb",
      "original": "newrepublic-2022-08-04T11:30:33.127755-04:00.jpg",
      "mtime": "1659630721",
      "size": "9605",
      "md5": "1f75f63bded3d889388b199038c3c002",
      "crc32": "d464d099",
      "sha1": "c3276e50e2bb43f8617b8690e5433e56ae154a7e"
    },
    {
      "name": "newrepublic-2022-08-04T14:46:37.733776-04:00.accessibility.json",
      "source": "original",
      "mtime": "1659638805",
      "size": "30799",
      "md5": "1d6699a1ca43021d5e962668aff56809",
      "crc32": "7d3b5779",
      "sha1": "514de3e19f3058e4375eaba1b3b7b17531f2773a",
      "format": "JSON"
    },
    {
      "name": "newrepublic-2022-08-04T14:46:37.733776-04:00.hyperlinks.json",
      "source": "original",
      "mtime": "1659638809",
      "size": "23414",
      "md5": "c4b0d453069f32ec87c618512eb5f194",
      "crc32": "8ee05d4a",
      "sha1": "00ac14488490ae7f1c9363bb8e27e42e14aa73cf",
      "format": "JSON"
    },
    {
      "name": "newrepublic-2022-08-04T14:46:37.733776-04:00.jpg",
      "source": "original",
      "mtime": "1659638799",
      "size": "247946",
      "md5": "541f833ea7e782f37c06f2429b6d7001",
      "crc32": "069496f3",
      "sha1": "3799d0abe5fa0661e5066d3ea5691ae1cc7d2b57",
      "format": "JPEG",
      "rotation": "0"
    },
    {
      "name": "newrepublic-2022-08-04T14:46:37.733776-04:00.lighthouse.json",
      "source": "original",
      "mtime": "1659638813",
      "size": "1467",
      "md5": "7e2d49de2ded42a42a47f7dc6cc7e3e7",
      "crc32": "3518119d",
      "sha1": "238951c6756b5e6d0a1f6783810110ca75fa41f3",
      "format": "JSON"
    },
    {
      "name": "newrepublic-2022-08-04T14:46:37.733776-04:00_thumb.jpg",
      "source": "derivative",
      "format": "JPEG Thumb",
      "original": "newrepublic-2022-08-04T14:46:37.733776-04:00.jpg",
      "mtime": "1659644511",
      "size": "9682",
      "md5": "63475a67162a147594fbb04863752e59",
      "crc32": "3116aa92",
      "sha1": "6f944a486448db6f1793a94830e1e76e07235bd4"
    },
    {
      "name": "newrepublic-2022-08-04T23:25:51.738695-04:00.accessibility.json",
      "source": "original",
      "mtime": "1659669954",
      "size": "30407",
      "md5": "c4f99a8b7a260713c20bdcd117e4eb69",
      "crc32": "78697ff3",
      "sha1": "444629e6abb8ee6dd64e732d5396dd7a3cd57a47",
      "format": "JSON"
    },
    {
      "name": "newrepublic-2022-08-04T23:25:51.738695-04:00.hyperlinks.json",
      "source": "original",
      "mtime": "1659669956",
      "size": "23483",
      "md5": "27981e10ea6925eb0386da770400a51c",
      "crc32": "d4dca03b",
      "sha1": "ecd35258ba00438c60383e0e8ebc97fe4442352a",
      "format": "JSON"
    },
    {
      "name": "newrepublic-2022-08-04T23:25:51.738695-04:00.jpg",
      "source": "original",
      "mtime": "1659669953",
      "size": "241903",
      "md5": "345e33c296050b5fc8521bd4ea52adfb",
      "crc32": "cbbb0937",
      "sha1": "88eb0b70789f1798997b176bb529841cfb0e04c6",
      "format": "JPEG",
      "rotation": "0"
    },
    {
      "name": "newrepublic-2022-08-04T23:25:51.738695-04:00.lighthouse.json",
      "source": "original",
      "mtime": "1659669958",
      "size": "1468",
      "md5": "5c580bfc55121e9dfac26a54fa744a80",
      "crc32": "5321f988",
      "sha1": "752cb29372806e9b38ecd5c173adff730f5cf375",
      "format": "JSON"
    },
    {
      "name": "newrepublic-2022-08-04T23:25:51.738695-04:00_thumb.jpg",
      "source": "derivative",
      "format": "JPEG Thumb",
      "original": "newrepublic-2022-08-04T23:25:51.738695-04:00.jpg",
      "mtime": "1659673391",
      "size": "9751",
      "md5": "94bb1ccaefd0862152e1dc405fc4d97e",
      "crc32": "3569643f",
      "sha1": "3528e0106c852678cabb919e194dfc257d049cb9"
    },
    {
      "name": "newrepublic-2022-08-05T13:31:48.848971-04:00.accessibility.json",
      "source": "original",
      "mtime": "1659720712",
      "size": "30460",
      "md5": "5f807db95d0eb918032873f676c6b348",
      "crc32": "7012ba43",
      "sha1": "2d01a941487dd9ddab0cec03e436f338289daa78",
      "format": "JSON"
    },
    {
      "name": "newrepublic-2022-08-05T13:31:48.848971-04:00.hyperlinks.json",
      "source": "original",
      "mtime": "1659720714",
      "size": "23218",
      "md5": "ff038b704992b85d2317f47778806ca5",
      "crc32": "1c0c1f3a",
      "sha1": "707a4450c517b3d4ccc7ff577b761e8438a02839",
      "format": "JSON"
    },
    {
      "name": "newrepublic-2022-08-05T13:31:48.848971-04:00.jpg",
      "source": "original",
      "mtime": "1659720710",
      "size": "246526",
      "md5": "6470d2614f50ccee6f7f22ca360afd29",
      "crc32": "12fb1be2",
      "sha1": "27422b402154385d73b6fa8cd8addd7787359027",
      "format": "JPEG",
      "rotation": "0"
    },
    {
      "name": "newrepublic-2022-08-05T13:31:48.848971-04:00.lighthouse.json",
      "source": "original",
      "mtime": "1659720715",
      "size": "1466",
      "md5": "c0b3581d3f0c781d749541d15e8703a8",
      "crc32": "5e68e973",
      "sha1": "3b7a1e32c9867c026af3fff1518b6386193a2086",
      "format": "JSON"
    },
    {
      "name": "newrepublic-2022-08-05T13:31:48.848971-04:00.wayback.json",
      "source": "original",
      "mtime": "1659720717",
      "size": "21413",
      "md5": "2068554cbfacf87e61ae686dbc63c7f7",
      "crc32": "7267a702",
      "sha1": "4b4299d178dbeb5d6511a71af9a2f830da3052ea",
      "format": "JSON"
    },
    {
      "name": "newrepublic-2022-08-05T13:31:48.848971-04:00_thumb.jpg",
      "source": "derivative",
      "format": "JPEG Thumb",
      "original": "newrepublic-2022-08-05T13:31:48.848971-04:00.jpg",
      "mtime": "1659720941",
      "size": "9783",
      "md5": "7aa5e8cc2dc34ecddd0cc98568c959c3",
      "crc32": "d804793c",
      "sha1": "6c9df8887ea2fb20d98dcbab908cc74dcb874949"
    },
    {
      "name": "newrepublic-2022-08-05T14:53:35.204908-04:00.accessibility.json",
      "source": "original",
      "mtime": "1659725619",
      "size": "30559",
      "md5": "59fa96601e99f85ac4d599e63a9f6615",
      "crc32": "ce4aa2d4",
      "sha1": "31efa65858cd7e42207c5d6d00d07fd2fcf749e9",
      "format": "JSON"
    },
    {
      "name": "newrepublic-2022-08-05T14:53:35.204908-04:00.hyperlinks.json",
      "source": "original",
      "mtime": "1659725622",
      "size": "23218",
      "md5": "bcfd87aecb64455fe20c51f17f1e1452",
      "crc32": "591b4f00",
      "sha1": "518ab5ebd09c898a4cd360365788af214f3dd994",
      "format": "JSON"
    },
    {
      "name": "newrepublic-2022-08-05T14:53:35.204908-04:00.jpg",
      "source": "original",
      "mtime": "1659725616",
      "size": "247024",
      "md5": "ea19cec9e9d5d539724b7e5c58f6fdd7",
      "crc32": "53435a7a",
      "sha1": "c6eb4ab55ac351fd28eb908c4fea20b8c1700cf4",
      "format": "JPEG",
      "rotation": "0"
    },
    {
      "name": "newrepublic-2022-08-05T14:53:35.204908-04:00.lighthouse.json",
      "source": "original",
      "mtime": "1659725623",
      "size": "1466",
      "md5": "9944f03737f435e9ceed0b7d3166560b",
      "crc32": "76aff069",
      "sha1": "e050f609b83084c8bd8a938c294c59976dd66a75",
      "format": "JSON"
    },
    {
      "name": "newrepublic-2022-08-05T14:53:35.204908-04:00.wayback.json",
      "source": "original",
      "mtime": "1659725624",
      "size": "21618",
      "md5": "f6ee44346a4f8bdb993e59125858b085",
      "crc32": "2cbe6e9d",
      "sha1": "f19eb9097310970acfd6ad22b607e196c0c7bd97",
      "format": "JSON"
    },
    {
      "name": "newrepublic-2022-08-05T14:53:35.204908-04:00_thumb.jpg",
      "source": "derivative",
      "format": "JPEG Thumb",
      "original": "newrepublic-2022-08-05T14:53:35.204908-04:00.jpg",
      "mtime": "1659725904",
      "size": "9786",
      "md5": "1e25cf990decc553abd3090be72fd7d2",
      "crc32": "4a058497",
      "sha1": "4d1ab4f70ec66c5cdc33633448eb44f7cc929ce3"
    },
    {
      "name": "newrepublic-2022-08-06T00:56:38.715390-04:00.accessibility.json",
      "source": "original",
      "mtime": "1659761803",
      "size": "29990",
      "md5": "07e5080d7d06e89fe214ce89571da24b",
      "crc32": "a7778184",
      "sha1": "280481637f73e193e0b55cf9b3c62eaccc38a672",
      "format": "JSON"
    },
    {
      "name": "newrepublic-2022-08-06T00:56:38.715390-04:00.hyperlinks.json",
      "source": "original",
      "mtime": "1659761805",
      "size": "23465",
      "md5": "7db7c29f69eacdf0c9199ba1d72e1ee9",
      "crc32": "cc8d4ed5",
      "sha1": "1f7e86f918d5eb99bad9aac00dda27f7f2233157",
      "format": "JSON"
    },
    {
      "name": "newrepublic-2022-08-06T00:56:38.715390-04:00.jpg",
      "source": "original",
      "mtime": "1659761802",
      "size": "248403",
      "md5": "b9759edee0857426c8386acd459cb72a",
      "crc32": "d8439774",
      "sha1": "ad7c34b7c663a3f68611f3ce3efc47c41dfa6c90",
      "format": "JPEG",
      "rotation": "0"
    },
    {
      "name": "newrepublic-2022-08-06T00:56:38.715390-04:00.lighthouse.json",
      "source": "original",
      "mtime": "1659761806",
      "size": "1468",
      "md5": "b48a6d66938d1cd71ac55eff6ff208e0",
      "crc32": "6fc64904",
      "sha1": "bd0138fd5cbb853f012fca0bd33872456bf5d382",
      "format": "JSON"
    },
    {
      "name": "newrepublic-2022-08-06T00:56:38.715390-04:00.wayback.json",
      "source": "original",
      "mtime": "1659761808",
      "size": "202",
      "md5": "07e452389e857b7334503102fdd2cebf",
      "crc32": "55525c66",
      "sha1": "7ee6c0c3a091f70360ecaf47dab6b707a0ab4c8a",
      "format": "JSON"
    },
    {
      "name": "newrepublic-2022-08-06T00:56:38.715390-04:00_thumb.jpg",
      "source": "derivative",
      "format": "JPEG Thumb",
      "original": "newrepublic-2022-08-06T00:56:38.715390-04:00.jpg",
      "mtime": "1659761869",
      "size": "9425",
      "md5": "fc47d26f3c33bca5c469eb5c0ebcfe08",
      "crc32": "d9e95f36",
      "sha1": "883e277e0eca3dfedeccb5649d0c81ab7540df4a"
    },
    {
      "name": "newrepublic-2022-08-06T12:19:49.691970-04:00.accessibility.json",
      "source": "original",
      "mtime": "1659802793",
      "size": "31277",
      "md5": "373bb94460621592238d03d47277d1ee",
      "crc32": "c4b42234",
      "sha1": "4112fb6f55d1f075e72bede5de13c503fdf63fff",
      "format": "JSON"
    },
    {
      "name": "newrepublic-2022-08-06T12:19:49.691970-04:00.hyperlinks.json",
      "source": "original",
      "mtime": "1659802795",
      "size": "23435",
      "md5": "4f4226db0489a27f2d08e92175e6be3b",
      "crc32": "e3475226",
      "sha1": "1da0f03b7f1001bab42f26dc9327ef8638f2b0c5",
      "format": "JSON"
    },
    {
      "name": "newrepublic-2022-08-06T12:19:49.691970-04:00.jpg",
      "source": "original",
      "mtime": "1659802791",
      "size": "250691",
      "md5": "2a85babacddfb01f33b9473a7a68398e",
      "crc32": "96c0b2e9",
      "sha1": "483060d662e710466dc0eb58a1fc8c2b37b7bbbd",
      "format": "JPEG",
      "rotation": "0"
    },
    {
      "name": "newrepublic-2022-08-06T12:19:49.691970-04:00.lighthouse.json",
      "source": "original",
      "mtime": "1659802797",
      "size": "1468",
      "md5": "a41921c7b6f4038d2dea1280b0268389",
      "crc32": "3cc1d128",
      "sha1": "51728d6d5d031a591071478d2f260cc9cccc6768",
      "format": "JSON"
    },
    {
      "name": "newrepublic-2022-08-06T12:19:49.691970-04:00.wayback.json",
      "source": "original",
      "mtime": "1659802798",
      "size": "21520",
      "md5": "490676077345f0206470bd778ca09562",
      "crc32": "94003c36",
      "sha1": "b07f595a807193f6ecf33cc655c178a6b24f905d",
      "format": "JSON"
    },
    {
      "name": "newrepublic-2022-08-06T12:19:49.691970-04:00_thumb.jpg",
      "source": "derivative",
      "format": "JPEG Thumb",
      "original": "newrepublic-2022-08-06T12:19:49.691970-04:00.jpg",
      "mtime": "1659803033",
      "size": "9498",
      "md5": "6f856fd00753d40dd0440ca4582ea7ec",
      "crc32": "8ad37d16",
      "sha1": "5e330b9c863bdb0f4674299db8b11c6be7f1df33"
    },
    {
      "name": "newrepublic-2022-08-06T14:42:31.431814-04:00.accessibility.json",
      "source": "original",
      "mtime": "1659811355",
      "size": "31277",
      "md5": "373bb94460621592238d03d47277d1ee",
      "crc32": "c4b42234",
      "sha1": "4112fb6f55d1f075e72bede5de13c503fdf63fff",
      "format": "JSON"
    },
    {
      "name": "newrepublic-2022-08-06T14:42:31.431814-04:00.hyperlinks.json",
      "source": "original",
      "mtime": "1659811356",
      "size": "23435",
      "md5": "4f4226db0489a27f2d08e92175e6be3b",
      "crc32": "e3475226",
      "sha1": "1da0f03b7f1001bab42f26dc9327ef8638f2b0c5",
      "format": "JSON"
    },
    {
      "name": "newrepublic-2022-08-06T14:42:31.431814-04:00.jpg",
      "source": "original",
      "mtime": "1659811352",
      "size": "250691",
      "md5": "2a85babacddfb01f33b9473a7a68398e",
      "crc32": "96c0b2e9",
      "sha1": "483060d662e710466dc0eb58a1fc8c2b37b7bbbd",
      "format": "JPEG",
      "rotation": "0"
    },
    {
      "name": "newrepublic-2022-08-06T14:42:31.431814-04:00.lighthouse.json",
      "source": "original",
      "mtime": "1659811358",
      "size": "1468",
      "md5": "d2a725aefb7e06ad263239b598f8f307",
      "crc32": "e0543165",
      "sha1": "5c85fd0741fb1617727d7638c2fbfb12b9bbb6a3",
      "format": "JSON"
    },
    {
      "name": "newrepublic-2022-08-06T14:42:31.431814-04:00.wayback.json",
      "source": "original",
      "mtime": "1659811359",
      "size": "21572",
      "md5": "6d5cfbdc5c4d437fdfc5ff2b7e40453f",
      "crc32": "3e7d1f39",
      "sha1": "06112f8c355f8cd3e6de9d0f40b8c02f9d09c2f4",
      "format": "JSON"
    },
    {
      "name": "newrepublic-2022-08-06T14:42:31.431814-04:00_thumb.jpg",
      "source": "derivative",
      "format": "JPEG Thumb",
      "original": "newrepublic-2022-08-06T14:42:31.431814-04:00.jpg",
      "mtime": "1659811440",
      "size": "9498",
      "md5": "6f856fd00753d40dd0440ca4582ea7ec",
      "crc32": "8ad37d16",
      "sha1": "5e330b9c863bdb0f4674299db8b11c6be7f1df33"
    },
    {
      "name": "newrepublic-2022_archive.torrent",
      "source": "metadata",
      "btih": "73682765d8f2078e0ed2ecde15cc48d5e1af35ac",
      "mtime": "1659811444",
      "size": "55478",
      "md5": "30d40584ae0dcf3c88b383a28956fdb1",
      "crc32": "3467d63b",
      "sha1": "b5babe55f730bdaf8e34678660c01eaf279a0264",
      "format": "Archive BitTorrent"
    },
    {
      "name": "newrepublic-2022_files.xml",
      "source": "original",
      "format": "Metadata",
      "md5": "a9a38986327046f4b4bb93d9366c7c97",
      "summation": "md5"
    },
    {
      "name": "newrepublic-2022_meta.sqlite",
      "source": "original",
      "mtime": "1659811366",
      "size": "327680",
      "md5": "cd355fbe7fecadd654df327d2fbd0676",
      "crc32": "e3debf11",
      "sha1": "766a758a339de8d6382a7603f35e28fd0f39687b",
      "format": "Metadata"
    },
    {
      "name": "newrepublic-2022_meta.xml",
      "source": "original",
      "mtime": "1658374570",
      "size": "593",
      "md5": "325339b391f144de01765db22bed1c4b",
      "crc32": "1330e811",
      "sha1": "17f9cd52f7739f3d9ee6cdfce47dda87ad1577ee",
      "format": "Metadata"
    }
  ],
  "files_count": 257,
  "item_last_updated": 1659811444,
  "item_size": 18649853,
  "metadata": {
    "identifier": "newrepublic-2022",
    "collection": [
      "news-homepages",
      "additional_collections"
    ],
    "contributor": "https://homepages.news",
    "date": "2022",
    "mediatype": "image",
    "publisher": "https://newrepublic.com/",
    "scanner": "Internet Archive Python library 3.0.2",
    "title": "New Republic homepages in 2022",
    "uploader": "ben.welsh@gmail.com",
    "publicdate": "2022-07-21 03:36:10",
    "addeddate": "2022-07-21 03:36:10"
  },
  "server": "ia801507.us.archive.org",
  "uniq": 1699237373,
  "workable_servers": [
    "ia801507.us.archive.org",
    "ia601507.us.archive.org"
  ]
}